{
  "generated_at": "2026-05-06T12:28:20Z",
  "country": "Algeria",
  "total_stories": 100,
  "categories": [
    "Diplomacy",
    "Military",
    "Energy",
    "Economy",
    "Local Events"
  ],
  "stories": [
    {
      "title": "Everyone has their own prediction",
      "source": "Liberté Algérie",
      "url": "https://www.liberte-algerie.com/editorial/a-chacun-sa-prediction-6149",
      "published_date": "2026-05-06T12:00:00Z",
      "category": "Diplomacy"
    },
    {
      "title": "Algerian-Uzbek talks to expand trade exchange and launch investment partnerships",
      "source": "Echorouk Online",
      "url": "https://www.echoroukonline.com/%d9%85%d8%ad%d8%a7%d8%af%d8%ab%d8%a7%d8%aa-%d8%ac%d8%b2%d8%a7%d8%a6%d8%b1%d9%8a%d8%a9-%d8%a3%d9%88%d8%b2%d8%a8%d9%83%d9%8a%d8%a9-%d9%84%d8%aa%d9%88%d8%b3%d9%8a%d8%b9-%d8%a7%d9%84%d8%aa%d8%a8%d8%a7",
      "published_date": "2026-05-06T11:42:26Z",
      "category": "Diplomacy"
    },
    {
      "title": "A delegation of Algerian businessmen discusses enhancing investments with American officials",
      "source": "Echorouk Online",
      "url": "https://www.echoroukonline.com/%d9%88%d9%81%d8%af-%d8%b1%d8%ac%d8%a7%d9%84-%d8%a3%d8%b9%d9%85%d8%a7%d9%84-%d8%ac%d8%b2%d8%a7%d8%a6%d8%b1%d9%8a%d9%8a%d9%86-%d9%8a%d8%a8%d8%ad%d8%ab-%d8%aa%d8%b9%d8%b2%d9%8a%d8%b2-%d8%a7%d9%84%d8%a7",
      "published_date": "2026-05-06T10:09:25Z",
      "category": "Diplomacy"
    },
    {
      "title": "Good news for Algerians in the USA: a new consulate inaugurated in San Francisco",
      "source": "Algerie360",
      "url": "https://www.algerie360.com/bonne-nouvelle-pour-les-algeriens-aux-usa-un-nouveau-consulat-inaugure-a-san-francisco/",
      "published_date": "2026-05-06T09:15:46Z",
      "category": "Diplomacy"
    },
    {
      "title": "Five medals for Algeria on the first day of the African Swimming Championship",
      "source": "Ennahar Online",
      "url": "https://www.ennaharonline.com/%d8%ae%d9%85%d8%b3-%d9%85%d9%8a%d8%af%d8%a7%d9%84%d9%8a%d8%a7%d8%aa-%d9%84%d9%84%d8%ac%d8%b2%d8%a7%d8%a6%d8%b1-%d9%81%d9%8a-%d8%a7%d9%84%d9%8a%d9%88%d9%85-%d8%a7%d9%84%d8%a3%d9%88%d9%84-%d9%85%d9%86/",
      "published_date": "2026-05-05T21:16:15Z",
      "category": "Diplomacy"
    },
    {
      "title": "Azouz Begag, former French minister: 2027 French elections unlikely to change Franco-Algerian relations",
      "source": "Echorouk Online",
      "url": "https://www.echoroukonline.com/azouz-begag-former-french-minister-2027-french-elections-unlikely-to-change-franco-algerian-relations",
      "published_date": "2026-05-05T18:46:50Z",
      "category": "Diplomacy"
    },
    {
      "title": "Official decree: a national fund for the care of this category of victims",
      "source": "Algerie360",
      "url": "https://www.algerie360.com/decret-officiel-un-fonds-national-pour-la-prise-en-charge-de-cette-categorie-de-victimes/",
      "published_date": "2026-05-05T17:25:36Z",
      "category": "Diplomacy"
    },
    {
      "title": "Sabrina Sebaihi at TSA: “What I said to Macron about Algeria…”",
      "source": "TSA Algérie",
      "url": "https://www.tsa-algerie.com/sabrina-sebaihi-a-tsa-ce-que-jai-dit-a-macron-sur-lalgerie/",
      "published_date": "2026-05-05T17:11:58Z",
      "category": "Diplomacy"
    },
    {
      "title": "Hantavirus on a cruise ship, 3 deaths: why experts are worried",
      "source": "Algerie360",
      "url": "https://www.algerie360.com/hantavirus-sur-un-bateau-de-croisiere-3-deces-pourquoi-les-experts-sinquietent/",
      "published_date": "2026-05-05T15:57:14Z",
      "category": "Diplomacy"
    },
    {
      "title": "A young Franco-Algerian basketball player joins the Algerian team",
      "source": "TSA Algérie",
      "url": "https://www.tsa-algerie.com/une-jeune-basketteuse-franco-algerienne-rejoint-lequipe-dalgerie/",
      "published_date": "2026-05-05T15:53:11Z",
      "category": "Diplomacy"
    },
    {
      "title": "Payment of the 2nd tranche AADL 3: Will there be a reprieve for subscribers in difficulty?",
      "source": "Algerie360",
      "url": "https://www.algerie360.com/paiement-de-la-2eme-tranche-aadl-3-y-aura-t-il-un-sursis-pour-les-souscripteurs-en-difficulte/",
      "published_date": "2026-05-05T15:28:28Z",
      "category": "Diplomacy"
    },
    {
      "title": "Attaf receives the European Union Commissioner in charge of the Mediterranean",
      "source": "Ennahar Online",
      "url": "https://www.ennaharonline.com/%d8%b9%d8%b7%d8%a7%d9%81-%d9%8a%d8%b3%d8%aa%d9%82%d8%a8%d9%84-%d9%85%d9%81%d9%88%d8%b6%d8%a9-%d8%a7%d9%84%d8%a7%d8%aa%d8%ad%d8%a7%d8%af-%d8%a7%d9%84%d8%a3%d9%88%d8%b1%d9%88%d8%a8%d9%8a-%d8%a7%d9%84/",
      "published_date": "2026-05-05T11:51:41Z",
      "category": "Diplomacy"
    },
    {
      "title": "Commercial exchanges between Algeria and Mauritania amount to 500 million dollars",
      "source": "Echorouk Online",
      "url": "https://www.echoroukonline.com/%d8%a7%d9%84%d9%85%d8%a8%d8%a7%d8%af%d9%84%d8%a7%d8%aa-%d8%a7%d9%84%d8%aa%d8%ac%d8%a7%d8%b1%d9%8a%d8%a9-%d8%a8%d9%8a%d9%86-%d8%a7%d9%84%d8%ac%d8%b2%d8%a7%d8%a6%d8%b1-%d9%88%d9%85%d9%88%d8%b1%d9%8a",
      "published_date": "2026-05-05T11:28:33Z",
      "category": "Diplomacy"
    },
    {
      "title": "The American Embassy is open for employment in this position",
      "source": "Ennahar Online",
      "url": "https://www.ennaharonline.com/%d8%a7%d9%84%d8%b3%d9%81%d8%a7%d8%b1%d8%a9-%d8%a7%d9%84%d8%a3%d9%85%d8%b1%d9%8a%d9%83%d9%8a%d8%a9-%d8%aa%d9%81%d8%aa%d8%ad-%d8%a8%d8%a7%d8%a8-%d8%a7%d9%84%d8%aa%d9%88%d8%b8%d9%8a%d9%81-%d9%81%d9%8a/",
      "published_date": "2026-05-05T10:53:00Z",
      "category": "Diplomacy"
    },
    {
      "title": "Looted colonial property: a necklace looted from a tomb in Sétif on display in France",
      "source": "Algerie360",
      "url": "https://www.algerie360.com/biens-coloniaux-spolies-un-collier-pille-dans-une-tombe-a-setif-expose-en-france/",
      "published_date": "2026-05-05T09:54:34Z",
      "category": "Diplomacy"
    },
    {
      "title": "Signing a project to support the implementation of the digital transformation strategy 2025-2030",
      "source": "Echorouk Online",
      "url": "https://www.echoroukonline.com/%d8%aa%d9%88%d9%82%d9%8a%d8%b9-%d9%85%d8%b4%d8%b1%d9%88%d8%b9-%d9%84%d8%af%d8%b9%d9%85-%d8%aa%d9%86%d9%81%d9%8a%d8%b0-%d8%a7%d8%b3%d8%aa%d8%b1%d8%a7%d8%aa%d9%8a%d8%ac%d9%8a%d8%a9-%d8%a7%d9%84%d8%aa",
      "published_date": "2026-05-05T09:25:49Z",
      "category": "Diplomacy"
    },
    {
      "title": "France – Algeria: Sarah Knafo brings out her “crazy” figures",
      "source": "TSA Algérie",
      "url": "https://www.tsa-algerie.com/france-algerie-sarah-knafo-ressort-ses-chiffres-mabouls/",
      "published_date": "2026-05-05T07:15:35Z",
      "category": "Diplomacy"
    },
    {
      "title": "From Maryland...a remarkable Algerian presence at the “Select USA” investment summit",
      "source": "Ennahar Online",
      "url": "https://www.ennaharonline.com/%d9%85%d9%86-%d9%85%d9%8a%d8%b1%d9%8a%d9%84%d8%a7%d9%86%d8%af-%d8%ad%d8%b6%d9%88%d8%b1-%d8%ac%d8%b2%d8%a7%d8%a6%d8%b1%d9%8a-%d9%84%d8%a7%d9%81%d8%aa-%d9%81%d9%8a-%d9%82%d9%85%d8%a9-select-u/",
      "published_date": "2026-05-04T22:05:24Z",
      "category": "Diplomacy"
    },
    {
      "title": "The Algerian business delegation enjoys a special meeting with the director of the American Investment Summit",
      "source": "Echorouk Online",
      "url": "https://www.echoroukonline.com/%d9%88%d9%81%d8%af-%d8%b1%d8%ac%d8%a7%d9%84-%d8%a7%d9%84%d8%a3%d8%b9%d9%85%d8%a7%d9%84-%d8%a7%d9%84%d8%ac%d8%b2%d8%a7%d8%a6%d8%b1%d9%8a-%d9%8a%d8%ad%d8%b8%d9%89-%d8%a8%d9%84%d9%82%d8%a7%d8%a1-%d8%ae",
      "published_date": "2026-05-04T19:59:11Z",
      "category": "Diplomacy"
    },
    {
      "title": "Crises in Africa: Chanegriha criticizes “external agendas”",
      "source": "TSA Algérie",
      "url": "https://www.tsa-algerie.com/crises-en-afrique-chanegriha-fustige-des-agendas-exterieurs/",
      "published_date": "2026-05-04T19:50:50Z",
      "category": "Diplomacy"
    },
    {
      "title": "This is how Meloni commented on a fake photo of her that spread among Italians!",
      "source": "Echorouk Online",
      "url": "https://www.echoroukonline.com/%d9%87%d9%83%d8%b0%d8%a7-%d8%b9%d9%84%d9%91%d9%82%d8%aa-%d9%85%d9%8a%d9%84%d9%88%d9%86%d9%8a-%d8%b9%d9%84%d9%89-%d8%b5%d9%88%d8%b1%d8%a9-%d9%85%d8%b2%d9%8a%d9%81%d8%a9-%d9%84%d9%87%d8%a7-%d8%a7%d9%86",
      "published_date": "2026-05-06T11:24:29Z",
      "category": "Military"
    },
    {
      "title": "In France, Muslims caught between separatism and entryism",
      "source": "TSA Algérie",
      "url": "https://www.tsa-algerie.com/en-france-les-musulmans-pris-en-tenaille-entre-separatisme-et-entrisme/",
      "published_date": "2026-05-06T10:10:33Z",
      "category": "Military"
    },
    {
      "title": "Djelfa security forces arrest the thief of a Peugeot 404",
      "source": "Ennahar Online",
      "url": "https://www.ennaharonline.com/%d8%a3%d9%85%d9%86-%d8%a7%d9%84%d8%ac%d9%84%d9%81%d8%a9-%d9%8a%d8%b7%d9%8a%d8%ad-%d8%a8%d8%b3%d8%a7%d8%b1%d9%82-%d8%b3%d9%8a%d8%a7%d8%b1%d8%a9-%d8%a8%d9%8a%d8%ac%d9%88-404/",
      "published_date": "2026-05-05T19:20:15Z",
      "category": "Military"
    },
    {
      "title": "Opening of the International Forum on Water and Environment Sustainability",
      "source": "Ennahar Online",
      "url": "https://www.ennaharonline.com/%d8%a7%d9%81%d8%aa%d8%aa%d8%a7%d8%ad-%d8%a3%d8%b4%d8%ba%d8%a7%d9%84-%d9%85%d9%84%d8%aa%d9%82%d9%89-%d8%af%d9%88%d9%84%d9%8a-%d8%ad%d9%88%d9%84-%d8%a7%d8%b3%d8%aa%d8%af%d8%a7%d9%85%d8%a9-%d8%a7%d9%84/",
      "published_date": "2026-05-05T11:49:23Z",
      "category": "Military"
    },
    {
      "title": "Christophe Gleizes renounces his cassation appeal and relies on a presidential pardon",
      "source": "Algerie360",
      "url": "https://www.algerie360.com/christophe-gleizes-renonce-a-son-pourvoi-en-cassation-et-mise-sur-une-grace-presidentielle/",
      "published_date": "2026-05-05T11:44:03Z",
      "category": "Military"
    },
    {
      "title": "In the video: 22,485 hallucinogenic tablets were seized in the state of Tiaret and two people were arrested",
      "source": "Echorouk Online",
      "url": "https://www.echoroukonline.com/%d8%a8%d8%a7%d9%84%d9%81%d9%8a%d8%af%d9%8a%d9%88-%d8%ad%d8%ac%d8%b2-22485-%d9%82%d8%b1%d8%b5-%d9%85%d9%87%d9%84%d9%88%d8%b3-%d8%a8%d9%88%d9%84%d8%a7%d9%8a%d8%a9-%d8%aa%d9%8a%d8%a7%d8%b1%d8%aa-%d9%88",
      "published_date": "2026-05-05T10:52:03Z",
      "category": "Military"
    },
    {
      "title": "Scattered switches for blocked outlets",
      "source": "Echorouk Online",
      "url": "https://www.echoroukonline.com/%d9%85%d9%81%d8%a7%d8%aa%d9%8a%d8%ad-%d9%85%d8%a8%d8%b9%d8%ab%d8%b1%d8%a9-%d9%84%d9%85%d9%86%d8%a7%d9%81%d8%b0-%d9%85%d8%b3%d8%af%d9%88%d8%af%d8%a9",
      "published_date": "2026-05-04T19:23:39Z",
      "category": "Military"
    },
    {
      "title": "Fight against money laundering: Algerian banks obliged to know everything about their customers",
      "source": "TSA Algérie",
      "url": "https://www.tsa-algerie.com/lutte-anti-blanchiment-les-banques-algeriennes-obligees-de-tout-savoir-sur-leurs-clients/",
      "published_date": "2026-05-04T18:22:50Z",
      "category": "Military"
    },
    {
      "title": "Adrar: the “Baladna” mega-project launches its first harvest",
      "source": "Algerie360",
      "url": "https://www.algerie360.com/adrar-le-mega-projet-baladna-lance-sa-premiere-recolte/",
      "published_date": "2026-05-04T16:28:26Z",
      "category": "Military"
    },
    {
      "title": "Former President Blaise Compaoré sentenced to life for the assassination of Thomas Sankara",
      "source": "Liberté Algérie",
      "url": "https://www.liberte-algerie.com/flash-actualite/l-ex-president-blaise-compaore-condamne-a-vie-pour-l-assassinat-de-thomas-sankara-15",
      "published_date": "2026-05-04T13:00:00Z",
      "category": "Military"
    },
    {
      "title": "الفريق أول شنقريحة: المعضلات الأمنية في إفريقيا تتأثر بتداخل أجندات خارجية",
      "source": "Ennahar Online",
      "url": "https://www.ennaharonline.com/%d8%a7%d9%84%d9%81%d8%b1%d9%8a%d9%82-%d8%a3%d9%88%d9%84-%d8%b4%d9%86%d9%82%d8%b1%d9%8a%d8%ad%d8%a9-%d8%a7%d9%84%d9%85%d8%b9%d8%b6%d9%84%d8%a7%d8%aa-%d8%a7%d9%84%d8%a3%d9%85%d9%86%d9%8a%d8%a9-%d9%81/",
      "published_date": "2026-05-04T11:34:38Z",
      "category": "Military"
    },
    {
      "title": "Lieutenant General Chengriha supervises the forum “The Algerian Approach to Building Security and Peace in Africa”",
      "source": "Echorouk Online",
      "url": "https://www.echoroukonline.com/%d8%a7%d9%84%d9%81%d8%b1%d9%8a%d9%82-%d8%a3%d9%88%d9%84-%d8%b4%d9%86%d9%82%d8%b1%d9%8a%d8%ad%d8%a9-%d9%8a%d9%8f%d8%b4%d8%b1%d9%81-%d8%b9%d9%84%d9%89-%d9%85%d9%84%d8%aa%d9%82%d9%89-%d8%a7%d9%84%d9%85",
      "published_date": "2026-05-04T11:08:23Z",
      "category": "Military"
    },
    {
      "title": "An American frigate was targeted by two missiles near Hormuz",
      "source": "Echorouk Online",
      "url": "https://www.echoroukonline.com/%d8%a7%d8%b3%d8%aa%d9%87%d8%af%d8%a7%d9%81-%d9%81%d8%b1%d9%82%d8%a7%d8%b7%d8%a9-%d8%a3%d9%85%d8%b1%d9%8a%d9%83%d9%8a%d8%a9-%d8%a8%d8%b5%d8%a7%d8%b1%d9%88%d8%ae%d9%8a%d9%86-%d9%82%d8%b1%d8%a8-%d9%87",
      "published_date": "2026-05-04T11:03:20Z",
      "category": "Military"
    },
    {
      "title": "Lieutenant General Chengriha supervises a forum on the Algerian approach to building security and peace in Africa",
      "source": "Ennahar Online",
      "url": "https://www.ennaharonline.com/%d8%a7%d9%84%d9%81%d8%b1%d9%8a%d9%82-%d8%a3%d9%88%d9%84-%d8%b4%d9%86%d9%82%d8%b1%d9%8a%d8%ad%d8%a9-%d9%8a%d8%b4%d8%b1%d9%81-%d8%b9%d9%84%d9%89-%d9%85%d9%84%d8%aa%d9%82%d9%89-%d8%ad%d9%88%d9%84-%d8%a7/",
      "published_date": "2026-05-04T11:02:22Z",
      "category": "Military"
    },
    {
      "title": "Immediate pension for military personnel under 15 years of service under study",
      "source": "Echorouk Online",
      "url": "https://www.echoroukonline.com/%d8%a7%d9%84%d9%85%d8%b9%d8%a7%d8%b4-%d8%a7%d9%84%d9%81%d9%88%d8%b1%d9%8a-%d9%84%d9%84%d8%b9%d8%b3%d9%83%d8%b1%d9%8a%d9%8a%d9%86-%d8%af%d9%88%d9%86-15-%d8%b3%d9%86%d8%a9-%d8%ae%d8%af%d9%85%d8%a9",
      "published_date": "2026-05-03T19:30:01Z",
      "category": "Military"
    },
    {
      "title": "Iran and the weapon of mathematics",
      "source": "Echorouk Online",
      "url": "https://www.echoroukonline.com/%d8%a5%d9%8a%d8%b1%d8%a7%d9%86-%d9%88%d8%b3%d9%84%d8%a7%d8%ad%d9%8f-%d8%a7%d9%84%d8%b1%d9%8a%d8%a7%d8%b6%d9%8a%d8%a7%d8%aa",
      "published_date": "2026-05-03T18:46:02Z",
      "category": "Military"
    },
    {
      "title": "Ministry of Defense: Destruction of a significant amount of seized drugs",
      "source": "Echorouk Online",
      "url": "https://www.echoroukonline.com/%d9%88%d8%b2%d8%a7%d8%b1%d8%a9-%d8%a7%d9%84%d8%af%d9%81%d8%a7%d8%b9-%d8%a5%d8%aa%d9%84%d8%a7%d9%81-%d9%83%d9%85%d9%8a%d8%a9-%d9%85%d8%b9%d8%aa%d8%a8%d8%b1%d8%a9-%d9%85%d9%86-%d8%a7%d9%84%d9%85",
      "published_date": "2026-05-03T11:14:47Z",
      "category": "Military"
    },
    {
      "title": "Destroying more than 9,000 kilograms of cocaine and approximately 200 kilograms of cocaine and heroin",
      "source": "Ennahar Online",
      "url": "https://www.ennaharonline.com/%d8%a5%d8%aa%d9%84%d8%a7%d9%81-%d8%a3%d8%b2%d9%8a%d8%af-%d9%85%d9%86-9-%d8%a2%d9%84%d8%a7%d9%81-%d9%83%d9%84%d8%ba-%d9%83%d9%8a%d9%81-%d9%88%d9%82%d8%b1%d8%a7%d8%a8%d8%a9-200-%d9%83%d9%84%d8%ba/",
      "published_date": "2026-05-03T11:01:51Z",
      "category": "Military"
    },
    {
      "title": "Curfew extended by 45 days in the Sahel",
      "source": "Liberté Algérie",
      "url": "https://www.liberte-algerie.com/flash-actualite/le-couvre-feu-prolonge-de-45-jours-dans-le-sahel-17",
      "published_date": "2026-05-02T14:01:00Z",
      "category": "Military"
    },
    {
      "title": "Algeria: two armed foreign smugglers shot dead in the far south",
      "source": "TSA Algérie",
      "url": "https://www.tsa-algerie.com/algerie-deux-contrebandiers-etrangers-armes-abattus-dans-lextreme-sud/",
      "published_date": "2026-05-02T11:50:43Z",
      "category": "Military"
    },
    {
      "title": "Algeria to the rescue of an oil giant: the underside of a rare fuel export",
      "source": "Algerie360",
      "url": "https://www.algerie360.com/lalgerie-au-secours-dun-geant-de-carburant-les-dessous-dune-exportation-dessence-inedite/",
      "published_date": "2026-05-06T11:48:59Z",
      "category": "Energy"
    },
    {
      "title": "Signing a contract to implement a project on urban adaptation to climate change",
      "source": "Ennahar Online",
      "url": "https://www.ennaharonline.com/%d8%aa%d9%88%d9%82%d9%8a%d8%b9-%d8%b9%d9%82%d8%af-%d8%aa%d9%86%d9%81%d9%8a%d8%b0-%d9%85%d8%b4%d8%b1%d9%88%d8%b9-%d8%ad%d9%88%d9%84-%d8%a7%d9%84%d8%aa%d9%83%d9%8a%d9%81-%d8%a7%d9%84%d8%ad%d8%b6%d8%b1/",
      "published_date": "2026-05-06T10:25:39Z",
      "category": "Energy"
    },
    {
      "title": "Hydrocarbons in Algeria: $1 billion contract for an Italian-Egyptian consortium",
      "source": "TSA Algérie",
      "url": "https://www.tsa-algerie.com/hydrocarbures-en-algerie-contrat-dun-milliard-pour-un-consortium-italo-egyptien/",
      "published_date": "2026-05-06T06:12:45Z",
      "category": "Energy"
    },
    {
      "title": "Algeria strengthens its cooperation with the European Union in major energy projects",
      "source": "Ennahar Online",
      "url": "https://www.ennaharonline.com/%d8%a7%d9%84%d8%ac%d8%b2%d8%a7%d8%a6%d8%b1-%d8%aa%d8%b9%d8%b2%d8%b2-%d8%aa%d8%b9%d8%a7%d9%88%d9%86%d9%87%d8%a7-%d9%85%d8%b9-%d8%a7%d9%84%d8%a7%d8%aa%d8%ad%d8%a7%d8%af-%d8%a7%d9%84%d8%a3%d9%88%d8%b1/",
      "published_date": "2026-05-05T21:32:17Z",
      "category": "Energy"
    },
    {
      "title": "Minister of Hydrocarbons: “We call on foreign companies to seize the available investment opportunities and participate in the bidding round.”",
      "source": "Echorouk Online",
      "url": "https://www.echoroukonline.com/%d9%88%d8%b2%d9%8a%d8%b1-%d8%a7%d9%84%d9%85%d8%ad%d8%b1%d9%88%d9%82%d8%a7%d8%aa-%d9%86%d8%af%d8%b9%d9%88-%d8%a7%d9%84%d8%b4%d8%b1%d9%83%d8%a7%d8%aa-%d8%a7%d9%84%d8%a3%d8%ac%d9%86%d8%a8%d9%8a%d8%a9",
      "published_date": "2026-05-05T19:39:34Z",
      "category": "Energy"
    },
    {
      "title": "Hydrocarbons: A billion-dollar investment sealed between Algeria and Egypt",
      "source": "Algerie360",
      "url": "https://www.algerie360.com/hydrocarbures-un-investissement-dun-milliard-de-dollars-scelle-entre-lalgerie-et-legypte/",
      "published_date": "2026-05-05T17:19:14Z",
      "category": "Energy"
    },
    {
      "title": "Sonatrach acquires Chinese equipment for $103 million",
      "source": "TSA Algérie",
      "url": "https://www.tsa-algerie.com/sonatrach-acquiert-des-equipements-chinois-pour-103-millions/",
      "published_date": "2026-05-05T12:42:26Z",
      "category": "Energy"
    },
    {
      "title": "The Egyptian Minister of Petroleum and Mineral Resources embarks on a working visit to Algeria",
      "source": "Echorouk Online",
      "url": "https://www.echoroukonline.com/%d9%88%d8%b2%d9%8a%d8%b1-%d8%a7%d9%84%d8%a8%d8%aa%d8%b1%d9%88%d9%84-%d9%88%d8%a7%d9%84%d8%ab%d8%b1%d9%88%d8%a9-%d8%a7%d9%84%d9%85%d8%b9%d8%af%d9%86%d9%8a%d8%a9-%d8%a7%d9%84%d9%85%d8%b5%d8%b1%d9%8a",
      "published_date": "2026-05-05T11:49:52Z",
      "category": "Energy"
    },
    {
      "title": "Hydrocarbons: the clear signal from Algiers to the EU during the visit of European Commissioner Šuica",
      "source": "Algerie360",
      "url": "https://www.algerie360.com/hydrocarbures-le-signal-clair-dalger-a-lue-lors-de-la-visite-de-la-commissaire-europeenne-suica/",
      "published_date": "2026-05-05T11:41:03Z",
      "category": "Energy"
    },
    {
      "title": "The Egyptian Minister of Petroleum and Mineral Resources is on a working visit to Algeria",
      "source": "Ennahar Online",
      "url": "https://www.ennaharonline.com/%d9%88%d8%b2%d9%8a%d8%b1-%d8%a7%d9%84%d8%a8%d8%aa%d8%b1%d9%88%d9%84-%d9%88%d8%a7%d9%84%d8%ab%d8%b1%d9%88%d8%a9-%d8%a7%d9%84%d9%85%d8%b9%d8%af%d9%86%d9%8a%d8%a9-%d8%a7%d9%84%d9%85%d8%b5%d8%b1%d9%8a/",
      "published_date": "2026-05-05T11:29:17Z",
      "category": "Energy"
    },
    {
      "title": "Gas: Qatar renews state of force majeure",
      "source": "TSA Algérie",
      "url": "https://www.tsa-algerie.com/gaz-le-qatar-reconduit-letat-de-force-majeure/",
      "published_date": "2026-05-05T06:17:08Z",
      "category": "Energy"
    },
    {
      "title": "Sidi El Houari: Sonatrach and Sonelgaz are committed to the rehabilitation of the historic district of Oran",
      "source": "Algerie360",
      "url": "https://www.algerie360.com/sidi-el-houari-sonatrach-et-sonelgaz-sengagent-pour-la-rehabilitation-du-quartier-historique-doran/",
      "published_date": "2026-05-04T19:19:04Z",
      "category": "Energy"
    },
    {
      "title": "Building permit: Ghrieb’s new decree which marks the end of bureaucracy in real estate",
      "source": "Algerie360",
      "url": "https://www.algerie360.com/permis-de-construire-le-nouveau-decret-de-ghrieb-qui-signe-la-fin-de-la-bureaucratie-dans-limmobilier/",
      "published_date": "2026-05-04T13:16:14Z",
      "category": "Energy"
    },
    {
      "title": "Unprecedented facilities for building permits...and these are the deadlines!",
      "source": "Echorouk Online",
      "url": "https://www.echoroukonline.com/%d8%aa%d8%b3%d9%87%d9%8a%d9%84%d8%a7%d8%aa-%d8%ba%d9%8a%d8%b1-%d9%85%d8%b3%d8%a8%d9%88%d9%82%d8%a9-%d9%81%d9%8a-%d8%b1%d8%ae%d8%b5-%d8%a7%d9%84%d8%a8%d9%86%d8%a7%d8%a1-%d9%88%d9%87%d8%b0%d9%87",
      "published_date": "2026-05-03T19:20:24Z",
      "category": "Energy"
    },
    {
      "title": "OPEC+: first decision by Algeria and 6 countries after the departure of the Emirates",
      "source": "Algerie360",
      "url": "https://www.algerie360.com/opep-premiere-decision-de-lalgerie-et-6-pays-apres-le-depart-des-emirats/",
      "published_date": "2026-05-03T14:16:56Z",
      "category": "Energy"
    },
    {
      "title": "Oil: Algeria increases its production by 6,000 barrels/day",
      "source": "TSA Algérie",
      "url": "https://www.tsa-algerie.com/petrole-lalgerie-augmente-sa-production-de-6-000-barils-jour/",
      "published_date": "2026-05-03T14:05:42Z",
      "category": "Energy"
    },
    {
      "title": "President Tebboune on the Emirates: “End of the speech, the book is closed”",
      "source": "Echorouk Online",
      "url": "https://www.echoroukonline.com/videotebboune-a-propos-des-emirats-fin-du-discours-le-livre-est-ferme",
      "published_date": "2026-05-03T10:20:01Z",
      "category": "Energy"
    },
    {
      "title": "Algeria is the second largest gas consumer in Africa and its largest exporter",
      "source": "Echorouk Online",
      "url": "https://www.echoroukonline.com/%d8%a7%d9%84%d8%ac%d8%b2%d8%a7%d8%a6%d8%b1-%d8%ab%d8%a7%d9%86%d9%8a-%d8%a3%d9%83%d8%a8%d8%b1-%d9%85%d8%b3%d8%aa%d9%87%d9%84%d9%83-%d9%84%d9%84%d8%ba%d8%a7%d8%b2-%d9%81%d9%8a-%d8%a5%d9%81%d8%b1%d9%8a",
      "published_date": "2026-05-03T09:59:15Z",
      "category": "Energy"
    },
    {
      "title": "“The speech is over and the book is folded.” The UAE’s exit from OPEC is a “storm in a teacup!”",
      "source": "Echorouk Online",
      "url": "https://www.echoroukonline.com/%d8%a7%d9%86%d8%aa%d9%87%d9%89-%d8%a7%d9%84%d8%ae%d8%b7%d8%a7%d8%a8-%d9%88%d8%b7%d9%88%d9%8a-%d8%a7%d9%84%d9%83%d8%aa%d8%a7%d8%a8-%d8%ae%d8%b1%d9%88%d8%ac-%d8%a7%d9%84%d8%a5%d9%85",
      "published_date": "2026-05-03T09:42:31Z",
      "category": "Energy"
    },
    {
      "title": "Braza Olive brand wins the award for best organic virgin olive oil in Algeria",
      "source": "Ennahar Online",
      "url": "https://www.ennaharonline.com/%d8%a7%d9%84%d8%b9%d9%84%d8%a7%d9%85%d8%a9-%d8%a7%d9%84%d8%aa%d8%ac%d8%a7%d8%b1%d9%8a%d8%a9-braza-olive-%d8%aa%d9%81%d9%88%d8%b2-%d8%a8%d8%ac%d8%a7%d8%a6%d8%b2%d8%a9-%d8%a3%d9%81%d8%b6%d9%84-%d8%b2/",
      "published_date": "2026-05-01T21:19:46Z",
      "category": "Energy"
    },
    {
      "title": "Preparing a national reference for industrial competencies to adapt training to the labor market",
      "source": "Echorouk Online",
      "url": "https://www.echoroukonline.com/%d8%a5%d8%b9%d8%af%d8%a7%d8%af-%d9%85%d8%b1%d8%ac%d8%b9-%d9%88%d8%b7%d9%86%d9%8a-%d9%84%d9%84%d9%83%d9%81%d8%a7%d8%a1%d8%a7%d8%aa-%d8%a7%d9%84%d8%b5%d9%86%d8%a7%d8%b9%d9%8a%d8%a9-%d9%84%d8%aa%d9%83",
      "published_date": "2026-05-06T12:05:49Z",
      "category": "Economy"
    },
    {
      "title": "International Monetary Fund: Algeria's economy is likely to reach $317 billion in 2026",
      "source": "Echorouk Online",
      "url": "https://www.echoroukonline.com/%d8%b5%d9%86%d8%af%d9%88%d9%82-%d8%a7%d9%84%d9%86%d9%82%d8%af-%d8%a7%d9%84%d8%af%d9%88%d9%84%d9%8a-%d8%a7%d9%82%d8%aa%d8%b5%d8%a7%d8%af-%d8%a7%d9%84%d8%ac%d8%b2%d8%a7%d8%a6%d8%b1-%d9%85%d8%b1%d8%b4",
      "published_date": "2026-05-06T10:45:40Z",
      "category": "Economy"
    },
    {
      "title": "Tennis Port receives 11,600 Romanian sheep",
      "source": "Ennahar Online",
      "url": "https://www.ennaharonline.com/%d9%85%d9%8a%d9%86%d8%a7%d8%a1-%d8%aa%d9%86%d8%b3-%d9%8a%d8%b3%d8%aa%d9%82%d8%a8%d9%84-11600-%d8%b1%d8%a3%d8%b3-%d8%ba%d9%86%d9%85-%d8%b1%d9%88%d9%85%d8%a7%d9%86%d9%8a/",
      "published_date": "2026-05-06T10:26:47Z",
      "category": "Economy"
    },
    {
      "title": "1ʳᵉ in the Maghreb: the IMF validates the jump in Algeria’s GDP towards the 400 billion mark set by Tebboune",
      "source": "Algerie360",
      "url": "https://www.algerie360.com/1%ca%b3%e1%b5%89-au-maghreb-le-fmi-valide-le-bond-du-pib-de-lalgerie-vers-le-cap-des-400-mds-fixe-par-tebboune/",
      "published_date": "2026-05-06T09:38:51Z",
      "category": "Economy"
    },
    {
      "title": "Cereal harvest: Algeria deploys 1,100 combine harvesters",
      "source": "TSA Algérie",
      "url": "https://www.tsa-algerie.com/recolte-des-cereales-lalgerie-deploie-1-100-moissonneuses-batteuses/",
      "published_date": "2026-05-06T09:16:28Z",
      "category": "Economy"
    },
    {
      "title": "IMF: Algeria's GDP will exceed $317 billion in 2026",
      "source": "TSA Algérie",
      "url": "https://www.tsa-algerie.com/fmi-le-pib-de-lalgerie-va-depasser-317-milliards-en-2026/",
      "published_date": "2026-05-05T20:28:58Z",
      "category": "Economy"
    },
    {
      "title": "These are cases of tax exemption... and building settlement fines are not concerned!",
      "source": "Echorouk Online",
      "url": "https://www.echoroukonline.com/%d9%87%d8%b0%d9%87-%d8%ad%d8%a7%d9%84%d8%a7%d8%aa-%d8%a7%d9%84%d8%a5%d8%b9%d9%81%d8%a7%d8%a1-%d9%85%d9%86-%d8%a7%d9%84%d8%b6%d8%b1%d8%a7%d8%a6%d8%a8-%d9%88%d8%ba%d8%b1%d8%a7%d9%85%d8%a7%d8%aa-%d8%aa",
      "published_date": "2026-05-05T19:25:52Z",
      "category": "Economy"
    },
    {
      "title": "The Ministry of Labor opens the file for implementing professional dispute rulings",
      "source": "Echorouk Online",
      "url": "https://www.echoroukonline.com/%d9%88%d8%b2%d8%a7%d8%b1%d8%a9-%d8%a7%d9%84%d8%b9%d9%85%d9%84-%d8%aa%d9%81%d8%aa%d8%ad-%d9%85%d9%84%d9%81-%d8%aa%d9%86%d9%81%d9%8a%d8%b0-%d8%a3%d8%ad%d9%83%d8%a7%d9%85-%d8%a7%d9%84%d9%86%d8%b2%d8%a7",
      "published_date": "2026-05-05T19:16:01Z",
      "category": "Economy"
    },
    {
      "title": "Minister of Commerce: The Commercial Activities Project dedicates the integrity of transactions and improving the quality of data",
      "source": "Ennahar Online",
      "url": "https://www.ennaharonline.com/%d9%88%d8%b2%d9%8a%d8%b1%d8%a9-%d8%a7%d9%84%d8%aa%d8%ac%d8%a7%d8%b1%d8%a9-%d9%85%d8%b4%d8%b1%d9%88%d8%b9-%d9%85%d9%85%d8%a7%d8%b1%d8%b3%d8%a9-%d8%a7%d9%84%d8%a3%d9%86%d8%b4%d8%b7%d8%a9-%d8%a7%d9%84/",
      "published_date": "2026-05-05T11:55:54Z",
      "category": "Economy"
    },
    {
      "title": "Imported sheep: this common practice among Algerians can kill them, warns a veterinarian",
      "source": "Algerie360",
      "url": "https://www.algerie360.com/mouton-importes-cette-pratique-courante-chez-les-algeriens-peut-les-tuer-avertit-une-veterinaire/",
      "published_date": "2026-05-05T11:53:40Z",
      "category": "Economy"
    },
    {
      "title": "The role of the constitutional judiciary in preserving rights and freedoms.. This is what Asalawi said",
      "source": "Echorouk Online",
      "url": "https://www.echoroukonline.com/%d8%af%d9%88%d8%b1-%d8%a7%d9%84%d9%82%d8%b6%d8%a7%d8%a1-%d8%a7%d9%84%d8%af%d8%b3%d8%aa%d9%88%d8%b1%d9%8a-%d9%81%d9%8a-%d8%b5%d9%88%d9%86-%d8%a7%d9%84%d8%ad%d9%82%d9%88%d9%82-%d9%88%d8%a7%d9%84%d8%ad",
      "published_date": "2026-05-05T11:34:06Z",
      "category": "Economy"
    },
    {
      "title": "Baladna Algeria: the giant farm carries out its first harvest",
      "source": "TSA Algérie",
      "url": "https://www.tsa-algerie.com/baladna-algerie-la-ferme-geante-effectue-sa-premiere-recolte/",
      "published_date": "2026-05-05T11:01:54Z",
      "category": "Economy"
    },
    {
      "title": "Investment and energy: Algerian bosses arrive in force in the United States",
      "source": "TSA Algérie",
      "url": "https://www.tsa-algerie.com/investissement-et-energie-les-patrons-algeriens-debarquent-en-force-aux-etats-unis/",
      "published_date": "2026-05-05T10:46:28Z",
      "category": "Economy"
    },
    {
      "title": "Patrick Martin: “Other countries are taking France’s place in Algeria”",
      "source": "TSA Algérie",
      "url": "https://www.tsa-algerie.com/patrick-martin-dautres-pays-prennent-la-place-de-la-france-en-algerie/",
      "published_date": "2026-05-05T10:21:52Z",
      "category": "Economy"
    },
    {
      "title": "Eid El-Adha: you can now collect your imported sheep, here's how it works",
      "source": "Algerie360",
      "url": "https://www.algerie360.com/aid-el-adha-vous-pouvez-desormais-recuperer-votre-mouton-importe-voici-comment-ca-se-passe/",
      "published_date": "2026-05-05T09:36:31Z",
      "category": "Economy"
    },
    {
      "title": "Legislation July 2.. Organizing electoral districts abroad and the number of seats required to be filled",
      "source": "Ennahar Online",
      "url": "https://www.ennaharonline.com/%d8%aa%d8%b4%d8%b1%d9%8a%d8%b9%d9%8a%d8%a7%d8%aa-2-%d8%ac%d9%88%d9%8a%d9%84%d9%8a%d8%a9-%d8%aa%d9%86%d8%b8%d9%8a%d9%85-%d8%a7%d9%84%d8%af%d9%88%d8%a7%d8%a6%d8%b1-%d8%a7%d9%84%d8%a7%d9%86%d8%aa%d8%ae/",
      "published_date": "2026-05-04T21:13:37Z",
      "category": "Economy"
    },
    {
      "title": "Mobilis wins the Sustainable Governance Award in Corporate Social Responsibility",
      "source": "Ennahar Online",
      "url": "https://www.ennaharonline.com/%d9%85%d9%88%d8%a8%d9%8a%d9%84%d9%8a%d8%b3-%d8%aa%d9%81%d9%88%d8%b2-%d8%a8%d8%ac%d8%a7%d8%a6%d8%b2%d8%a9-%d8%a7%d9%84%d8%ad%d9%88%d9%83%d9%85%d8%a9-%d8%a7%d9%84%d9%85%d8%b3%d8%aa%d8%af%d8%a7%d9%85/",
      "published_date": "2026-05-04T20:57:43Z",
      "category": "Economy"
    },
    {
      "title": "This is how institutions avoid paying training and apprenticeship fees with conditions!",
      "source": "Echorouk Online",
      "url": "https://www.echoroukonline.com/%d9%87%d9%83%d8%b0%d8%a7-%d8%aa%d8%aa%d9%81%d8%a7%d8%af%d9%89-%d8%a7%d9%84%d9%85%d8%a4%d8%b3%d8%b3%d8%a7%d8%aa-%d8%af%d9%81%d8%b9-%d8%b1%d8%b3%d9%88%d9%85-%d8%a7%d9%84%d8%aa%d9%83%d9%88%d9%8a%d9%86",
      "published_date": "2026-05-04T19:49:22Z",
      "category": "Economy"
    },
    {
      "title": "The success of the automobile industry in Algeria begins with iron and plastic!",
      "source": "Echorouk Online",
      "url": "https://www.echoroukonline.com/%d9%86%d8%ac%d8%a7%d8%ad-%d8%b5%d9%86%d8%a7%d8%b9%d8%a9-%d8%a7%d9%84%d8%b3%d9%8a%d8%a7%d8%b1%d8%a7%d8%aa-%d9%81%d9%8a-%d8%a7%d9%84%d8%ac%d8%b2%d8%a7%d8%a6%d8%b1-%d9%8a%d8%a8%d8%af%d8%a3-%d9%85%d9%86",
      "published_date": "2026-05-04T19:49:11Z",
      "category": "Economy"
    },
    {
      "title": "Morocco: the World Bank overwhelms Mohammed VI",
      "source": "TSA Algérie",
      "url": "https://www.tsa-algerie.com/maroc-la-banque-mondiale-accable-mohammed-vi/",
      "published_date": "2026-05-04T19:00:12Z",
      "category": "Economy"
    },
    {
      "title": "How the 22 met at Lyes Derriche (July 25, 1954)",
      "source": "Liberté Algérie",
      "url": "https://www.liberte-algerie.com/videos/comment-les-22-se-sont-reunis-chez-lyes-derriche-25-juillet-1954-5",
      "published_date": "2026-05-06T15:06:00Z",
      "category": "Local Events"
    },
    {
      "title": "Millions of people lack food during Ramadan",
      "source": "Liberté Algérie",
      "url": "https://www.liberte-algerie.com/flash-actualite/des-millions-de-personnes-manquent-de-nourriture-durant-le-ramadan-13",
      "published_date": "2026-05-06T14:27:00Z",
      "category": "Local Events"
    },
    {
      "title": "Postponement until April 20 of the trial of the accused in the Metidji group affair",
      "source": "Liberté Algérie",
      "url": "https://www.liberte-algerie.com/flash-actualite/report-au-20-avril-du-proces-des-accuses-dans-l-affaire-du-groupe-metidji-16",
      "published_date": "2026-05-06T13:35:00Z",
      "category": "Local Events"
    },
    {
      "title": "Special bulletin: Very heavy rain across 24 states tomorrow, Thursday",
      "source": "Echorouk Online",
      "url": "https://www.echoroukonline.com/%d9%86%d8%b4%d8%b1%d9%8a%d8%a9-%d8%ae%d8%a7%d8%b5%d8%a9-%d8%a3%d9%85%d8%b7%d8%a7%d8%b1-%d8%ba%d8%b2%d9%8a%d8%b1%d8%a9-%d8%ac%d8%af%d8%a7-%d8%b9%d8%a8%d8%b1-24-%d9%88%d9%84%d8%a7%d9%8a%d8%a9-%d8%ba",
      "published_date": "2026-05-06T12:21:23Z",
      "category": "Local Events"
    },
    {
      "title": "Sila 2022: Ahmed Benzelikha author of “Les Dupes” (Casbah éditions)",
      "source": "Liberté Algérie",
      "url": "https://www.liberte-algerie.com/videos/sila-2022-ahmed-benzelikha-auteur-de-les-dupes-casbah-editions-4",
      "published_date": "2026-05-06T12:16:00Z",
      "category": "Local Events"
    },
    {
      "title": "Sila 2022: Adib Benazzi author of “Low tide” (Dalimen editions)",
      "source": "Liberté Algérie",
      "url": "https://www.liberte-algerie.com/videos/sila-2022-adib-benazzi-auteur-de-maree-basse-editions-dalimen",
      "published_date": "2026-05-06T12:12:00Z",
      "category": "Local Events"
    },
    {
      "title": "Naamoun begins his duties in “Al-Siyarabi” next week",
      "source": "Ennahar Online",
      "url": "https://www.ennaharonline.com/%d9%86%d8%b9%d9%85%d9%88%d9%86-%d9%8a%d8%a8%d8%a7%d8%b4%d8%b1-%d9%85%d9%87%d8%a7%d9%85%d9%87-%d9%81%d9%8a-%d8%a7%d9%84%d8%b3%d9%8a%d8%a7%d8%b1%d8%a8%d9%8a-%d8%a7%d9%84%d8%a3%d8%b3%d8%a8%d9%88/",
      "published_date": "2026-05-06T12:09:26Z",
      "category": "Local Events"
    },
    {
      "title": "Bouira...the start of drilling artesian wells with a depth of more than 1,200 metres",
      "source": "Ennahar Online",
      "url": "https://www.ennaharonline.com/%d8%a8%d9%88%d9%8a%d8%b1%d8%a9-%d8%a7%d9%86%d8%b7%d9%84%d8%a7%d9%82-%d8%ad%d9%81%d8%b1-%d8%a7%d9%84%d8%a2%d8%a8%d8%a7%d8%b1-%d8%a7%d9%84%d8%a7%d8%b1%d8%aa%d9%88%d8%a7%d8%b2%d9%8a%d8%a9-%d8%a8%d8%b9/",
      "published_date": "2026-05-06T12:06:16Z",
      "category": "Local Events"
    },
    {
      "title": "Sila 2022: “Le Hic” author of “Just for pleasure”",
      "source": "Liberté Algérie",
      "url": "https://www.liberte-algerie.com/videos/sila-2022-le-hic-auteur-de-juste-pour-le-plaisir-2",
      "published_date": "2026-05-06T12:01:00Z",
      "category": "Local Events"
    },
    {
      "title": "LA BOURGEOISE",
      "source": "Liberté Algérie",
      "url": "https://www.liberte-algerie.com/des-gens-et-des-faits/la-bourgeoise-376435",
      "published_date": "2026-05-06T12:00:00Z",
      "category": "Local Events"
    },
    {
      "title": "The “Freedom” documentation preserved",
      "source": "Liberté Algérie",
      "url": "https://www.liberte-algerie.com/actualite/la-documentation-de-liberte-conservee-376439",
      "published_date": "2026-05-06T12:00:00Z",
      "category": "Local Events"
    },
    {
      "title": "“THE SACRIFICES...”",
      "source": "Liberté Algérie",
      "url": "https://www.liberte-algerie.com/des-gens-et-des-faits/les-sacrifices-376436",
      "published_date": "2026-05-06T12:00:00Z",
      "category": "Local Events"
    },
    {
      "title": "An air of “FREEDOM” goes away",
      "source": "Liberté Algérie",
      "url": "https://www.liberte-algerie.com/editorial/un-air-de-liberte-s-en-va-6150",
      "published_date": "2026-05-06T12:00:00Z",
      "category": "Local Events"
    },
    {
      "title": "Ménière's disease or Ménière's vertigo: what is it?",
      "source": "Liberté Algérie",
      "url": "https://www.liberte-algerie.com/la-rubrique-de-la-famille/maladie-de-meniere-ou-vertige-de-meniere-qu-est-ce-que-c-est-376442",
      "published_date": "2026-05-06T12:00:00Z",
      "category": "Local Events"
    },
    {
      "title": "Trajectory of a columnist in… Freedom",
      "source": "Liberté Algérie",
      "url": "https://www.liberte-algerie.com/actualite/trajectoire-d-un-chroniqueur-en-liberte-376438",
      "published_date": "2026-05-06T12:00:00Z",
      "category": "Local Events"
    },
    {
      "title": "The altar is erected",
      "source": "Liberté Algérie",
      "url": "https://www.liberte-algerie.com/editorial/l-autel-est-dresse-6148",
      "published_date": "2026-05-06T12:00:00Z",
      "category": "Local Events"
    },
    {
      "title": "Requiem",
      "source": "Liberté Algérie",
      "url": "https://www.liberte-algerie.com/editorial/requiem-6147",
      "published_date": "2026-05-06T12:00:00Z",
      "category": "Local Events"
    },
    {
      "title": "The feeling and the raw figure",
      "source": "Liberté Algérie",
      "url": "https://www.liberte-algerie.com/editorial/le-ressenti-et-le-chiffre-brut-6146",
      "published_date": "2026-05-06T12:00:00Z",
      "category": "Local Events"
    },
    {
      "title": "3 ministers before parliamentarians this Thursday",
      "source": "Echorouk Online",
      "url": "https://www.echoroukonline.com/3-%d9%88%d8%b2%d8%b1%d8%a7%d8%a1-%d8%a3%d9%85%d8%a7%d9%85-%d9%86%d9%88%d8%a7%d8%a8-%d8%a7%d9%84%d8%a8%d8%b1%d9%84%d9%85%d8%a7%d9%86-%d9%87%d8%b0%d8%a7-%d8%a7%d9%84%d8%ae%d9%85%d9%8a%d8%b3",
      "published_date": "2026-05-06T11:54:05Z",
      "category": "Local Events"
    },
    {
      "title": "Final exams...cheating and human framing: This is what the Minister of Education ordered",
      "source": "Ennahar Online",
      "url": "https://www.ennaharonline.com/%d8%a7%d9%84%d8%a7%d9%85%d8%aa%d8%ad%d8%a7%d9%86%d8%a7%d8%aa-%d8%a7%d9%84%d9%86%d9%87%d8%a7%d8%a6%d9%8a%d8%a9-%d8%a7%d9%84%d8%ba%d8%b4-%d9%88%d8%a7%d9%84%d8%aa%d8%a3%d8%b7%d9%8a%d8%b1-%d8%a7%d9%84/",
      "published_date": "2026-05-06T11:54:04Z",
      "category": "Local Events"
    }
  ]
}