{
  "generated_at": "2026-04-30T23:53:57Z",
  "country": "Algeria",
  "total_stories": 100,
  "categories": [
    "Diplomacy",
    "Military",
    "Energy",
    "Economy",
    "Local Events"
  ],
  "stories": [
    {
      "title": "Algeria–France: AFD reframes the far right on development aid",
      "source": "TSA Algérie",
      "url": "https://www.tsa-algerie.com/algerie-france-lafd-recadre-lextreme-droite-sur-laide-au-developpement/",
      "published_date": "2026-04-30T20:00:51Z",
      "category": "Diplomacy"
    },
    {
      "title": "Algeria crushes Moroccan “envelope maneuvers” in South Africa!!",
      "source": "Echorouk Online",
      "url": "https://www.echoroukonline.com/%d8%a7%d9%84%d8%ac%d8%b2%d8%a7%d8%a6%d8%b1-%d8%aa%d8%b3%d8%ad%d9%82-%d9%85%d9%86%d8%a7%d9%88%d8%b1%d8%a7%d8%aa-%d8%a7%d9%84%d8%a3%d8%b8%d8%b1%d9%81%d8%a9-%d8%a7%d9%84%d9%85%d8%ba%d8%b1%d8%a8%d9%8a",
      "published_date": "2026-04-30T19:59:57Z",
      "category": "Diplomacy"
    },
    {
      "title": "Shayeb looks at the readiness of the port of Alicante in preparation for the arrival of the community",
      "source": "Ennahar Online",
      "url": "https://www.ennaharonline.com/%d8%b4%d8%a7%d9%8a%d8%a8-%d9%8a%d9%82%d9%81-%d8%b9%d9%84%d9%89-%d8%ac%d8%a7%d9%87%d8%b2%d9%8a%d8%a9-%d9%85%d9%8a%d9%86%d8%a7%d8%a1-%d8%a3%d9%84%d9%8a%d9%83%d8%a7%d9%86%d8%aa%d9%8a-%d8%a7%d8%b3%d8%aa/",
      "published_date": "2026-04-30T19:04:26Z",
      "category": "Diplomacy"
    },
    {
      "title": "France – Algeria crisis: Amellal charges Bardella and Retailleau",
      "source": "TSA Algérie",
      "url": "https://www.tsa-algerie.com/crise-france-algerie-amellal-charge-bardella-et-retailleau/",
      "published_date": "2026-04-30T17:30:31Z",
      "category": "Diplomacy"
    },
    {
      "title": "Algeria and Russia are discussing deepening cooperation in industry",
      "source": "Echorouk Online",
      "url": "https://www.echoroukonline.com/%d8%a7%d9%84%d8%ac%d8%b2%d8%a7%d8%a6%d8%b1-%d9%88%d8%b1%d9%88%d8%b3%d9%8a%d8%a7-%d8%aa%d8%a8%d8%ad%d8%ab%d8%a7%d9%86-%d8%aa%d8%b9%d9%85%d9%8a%d9%82-%d8%a7%d9%84%d8%aa%d8%b9%d8%a7%d9%88%d9%86-%d9%81",
      "published_date": "2026-04-30T17:02:31Z",
      "category": "Diplomacy"
    },
    {
      "title": "Trafficking in psychotropic drugs from Turkey: 10 years in prison for an illegal driver",
      "source": "Algerie360",
      "url": "https://www.algerie360.com/trafic-de-psychotropes-depuis-la-turquie-10-ans-de-prison-pour-un-chauffeur-clandestin/",
      "published_date": "2026-04-30T16:31:59Z",
      "category": "Diplomacy"
    },
    {
      "title": "Attaf receives the President of the France-Algeria Association",
      "source": "Echorouk Online",
      "url": "https://www.echoroukonline.com/%d8%b9%d8%b7%d8%a7%d9%81-%d9%8a%d8%b3%d8%aa%d9%82%d8%a8%d9%84-%d8%b1%d8%a6%d9%8a%d8%b3%d8%a9-%d8%ac%d9%85%d8%b9%d9%8a%d8%a9-%d9%81%d8%b1%d9%86%d8%b3%d8%a7-%d8%a7%d9%84%d8%ac%d8%b2%d8%a7%d8%a6%d8%b1",
      "published_date": "2026-04-30T15:38:10Z",
      "category": "Diplomacy"
    },
    {
      "title": "France – Algeria flights: this company charges a supplement on tickets already purchased",
      "source": "Algerie360",
      "url": "https://www.algerie360.com/vols-france-algerie-cette-compagnie-fait-payer-un-supplement-sur-les-billets-deja-achetes/",
      "published_date": "2026-04-30T15:37:31Z",
      "category": "Diplomacy"
    },
    {
      "title": "President Tebboune on the occasion of May 1: Algeria is one of the countries that provides the most social coverage and care",
      "source": "Echorouk Online",
      "url": "https://www.echoroukonline.com/%d8%a7%d9%84%d8%b1%d8%a6%d9%8a%d8%b3-%d8%aa%d8%a8%d9%88%d9%86-%d8%a8%d9%85%d9%86%d8%a7%d8%b3%d8%a8%d8%a9-%d8%a7%d9%84%d9%81%d8%a7%d8%aa%d8%ad-%d9%85%d8%a7%d9%8a-%d8%a7%d9%84%d8%ac%d8%b2%d8%a7%d8%a6",
      "published_date": "2026-04-30T14:55:08Z",
      "category": "Diplomacy"
    },
    {
      "title": "Algérie Poste: a new service dedicated to this category of customers",
      "source": "Algerie360",
      "url": "https://www.algerie360.com/algerie-poste-un-nouveau-service-dedie-a-cette-categorie-de-clients/",
      "published_date": "2026-04-30T14:02:11Z",
      "category": "Diplomacy"
    },
    {
      "title": "An Algerian elected head of the Pan-African Parliament",
      "source": "TSA Algérie",
      "url": "https://www.tsa-algerie.com/un-algerien-elu-a-la-tete-du-parlement-panafricain/",
      "published_date": "2026-04-30T13:56:04Z",
      "category": "Diplomacy"
    },
    {
      "title": "The President of the Republic sends a message to Algerian pilgrims",
      "source": "Echorouk Online",
      "url": "https://www.echoroukonline.com/%d8%b1%d8%a6%d9%8a%d8%b3-%d8%a7%d9%84%d8%ac%d9%85%d9%87%d9%88%d8%b1%d9%8a%d8%a9-%d9%8a%d9%88%d8%ac%d9%87-%d8%b1%d8%b3%d8%a7%d9%84%d8%a9-%d8%a5%d9%84%d9%89-%d8%a7%d9%84%d8%ad%d8%ac%d8%a7%d8%ac-%d8%a7",
      "published_date": "2026-04-30T13:22:27Z",
      "category": "Diplomacy"
    },
    {
      "title": "Cup - Final: A great revenge at 5 p.m.!",
      "source": "DzFoot",
      "url": "https://www.dzfoot.com/football-en-algerie/coupe-finale-une-belle-revanche-a-17h-292186.html?utm_source=rss_feed&utm_medium=link&utm_campaign=unknown",
      "published_date": "2026-04-30T13:19:30Z",
      "category": "Diplomacy"
    },
    {
      "title": "Poland wants to establish its industry in Algeria: the great ambitions of this rapprochement revealed",
      "source": "Algerie360",
      "url": "https://www.algerie360.com/la-pologne-veut-implanter-son-industrie-en-algerie-les-grandes-ambitions-de-ce-rapprochement-devoilees/",
      "published_date": "2026-04-30T12:32:25Z",
      "category": "Diplomacy"
    },
    {
      "title": "Everyone has their own prediction",
      "source": "Liberté Algérie",
      "url": "https://www.liberte-algerie.com/editorial/a-chacun-sa-prediction-6149",
      "published_date": "2026-04-30T12:00:00Z",
      "category": "Diplomacy"
    },
    {
      "title": "EN: One last match against a Latin American selection?",
      "source": "DzFoot",
      "url": "https://www.dzfoot.com/equipes-nationales/en-un-dernier-match-contre-une-selection-latino-americaine-292183.html?utm_source=rss_feed&utm_medium=link&utm_campaign=unknown",
      "published_date": "2026-04-30T11:22:37Z",
      "category": "Diplomacy"
    },
    {
      "title": "A senior American official captivated by the charm of Algiers",
      "source": "TSA Algérie",
      "url": "https://www.tsa-algerie.com/un-haut-responsable-americain-subjugue-par-le-charme-dalger/",
      "published_date": "2026-04-30T10:35:50Z",
      "category": "Diplomacy"
    },
    {
      "title": "Algeria is strengthening its presence in the global nuclear disarmament file",
      "source": "Echorouk Online",
      "url": "https://www.echoroukonline.com/%d8%a7%d9%84%d8%ac%d8%b2%d8%a7%d8%a6%d8%b1-%d8%aa%d9%8f%d8%b9%d8%b2%d8%b2-%d8%ad%d8%b6%d9%88%d8%b1%d9%87%d8%a7-%d9%81%d9%8a-%d9%85%d9%84%d9%81-%d9%86%d8%b2%d8%b9-%d8%a7%d9%84%d8%b3%d9%84%d8%a7%d8%ad",
      "published_date": "2026-04-30T09:54:43Z",
      "category": "Diplomacy"
    },
    {
      "title": "“The mabouls know how to count”: Sarah Knafo brandishes her controversial 9 billion bill on Algeria",
      "source": "Algerie360",
      "url": "https://www.algerie360.com/les-mabouls-savent-compter-sarah-knafo-brandit-sa-facture-controversee-a-9-milliards-sur-lalgerie/",
      "published_date": "2026-04-30T09:31:57Z",
      "category": "Diplomacy"
    },
    {
      "title": "Hajj 2026.. The first flights of Algerian pilgrims begin from Houari Boumediene Airport",
      "source": "Ennahar Online",
      "url": "https://www.ennaharonline.com/%d8%ad%d8%ac-2026-%d8%a7%d9%86%d8%b7%d9%84%d8%a7%d9%82-%d8%a3%d9%88%d9%84%d9%89-%d8%b1%d8%ad%d9%84%d8%a7%d8%aa-%d8%a7%d9%84%d8%ad%d8%ac%d8%a7%d8%ac-%d8%a7%d9%84%d8%ac%d8%b2%d8%a7%d8%a6%d8%b1%d9%8a/",
      "published_date": "2026-04-29T19:47:28Z",
      "category": "Diplomacy"
    },
    {
      "title": "Appeal to the public regarding two fake doctors",
      "source": "Ennahar Online",
      "url": "https://www.ennaharonline.com/%d9%86%d8%af%d8%a7%d8%a1-%d9%84%d9%84%d8%ac%d9%85%d9%87%d9%88%d8%b1-%d8%a8%d8%ae%d8%b5%d9%88%d8%b5-%d8%b7%d8%a8%d9%8a%d8%a8%d9%8a%d9%86-%d9%85%d8%b2%d9%8a%d9%81%d9%8a%d9%86/",
      "published_date": "2026-04-30T19:26:39Z",
      "category": "Military"
    },
    {
      "title": "The National Gendarmerie in Tiaret sends an appeal to the public",
      "source": "Ennahar Online",
      "url": "https://www.ennaharonline.com/%d8%a7%d9%84%d8%af%d8%b1%d9%83-%d8%a7%d9%84%d9%88%d8%b7%d9%86%d9%8a-%d8%a8%d8%aa%d9%8a%d8%a7%d8%b1%d8%aa-%d9%8a%d9%88%d8%ac%d9%87-%d9%86%d8%af%d8%a7%d8%a1-%d9%84%d9%84%d8%ac%d9%85%d9%87%d9%88%d8%b1/",
      "published_date": "2026-04-30T18:35:21Z",
      "category": "Military"
    },
    {
      "title": "Algeria facing the war in Mali: what Abdelaziz Rahabi recommends",
      "source": "TSA Algérie",
      "url": "https://www.tsa-algerie.com/lalgerie-face-a-la-guerre-au-mali-ce-que-preconise-abdelaziz-rahabi/",
      "published_date": "2026-04-30T13:17:55Z",
      "category": "Military"
    },
    {
      "title": "Announcing the measures taken to secure the Republic Cup final match",
      "source": "Echorouk Online",
      "url": "https://www.echoroukonline.com/%d8%a7%d9%84%d8%a5%d8%b9%d9%84%d8%a7%d9%86-%d8%b9%d9%86-%d8%a7%d9%84%d8%a5%d8%ac%d8%b1%d8%a7%d8%a1%d8%a7%d8%aa-%d8%a7%d9%84%d9%85%d8%aa%d8%ae%d8%b0%d8%a9-%d9%84%d8%aa%d8%a3%d9%85%d9%8a%d9%86-%d9%85-4",
      "published_date": "2026-04-30T09:01:45Z",
      "category": "Military"
    },
    {
      "title": "Dismantling of a terrorist propaganda network: a former police officer at the heart of the affair",
      "source": "Algerie360",
      "url": "https://www.algerie360.com/demantelement-dun-reseau-de-propagande-terroriste-un-ancien-policier-au-coeur-de-laffaire/",
      "published_date": "2026-04-29T20:09:25Z",
      "category": "Military"
    },
    {
      "title": "The son of the late mujahid, Colonel Akli Mohand Olhaj, delivers rare revolutionary items to the Army Museum",
      "source": "Ennahar Online",
      "url": "https://www.ennaharonline.com/%d9%86%d8%ac%d9%84-%d8%a7%d9%84%d9%85%d8%ac%d8%a7%d9%87%d8%af-%d8%a7%d9%84%d9%85%d8%b1%d8%ad%d9%88%d9%85-%d8%a7%d9%84%d8%b9%d9%82%d9%8a%d8%af-%d8%a3%d9%83%d9%84%d9%8a-%d9%85%d8%ad%d9%86%d8%af-%d8%a3/",
      "published_date": "2026-04-29T18:16:57Z",
      "category": "Military"
    },
    {
      "title": "Former President Blaise Compaoré sentenced to life for the assassination of Thomas Sankara",
      "source": "Liberté Algérie",
      "url": "https://www.liberte-algerie.com/flash-actualite/l-ex-president-blaise-compaore-condamne-a-vie-pour-l-assassinat-de-thomas-sankara-15",
      "published_date": "2026-04-29T13:00:00Z",
      "category": "Military"
    },
    {
      "title": "8 kg of cocaine were seized, and more than two quintals of cocaine coming from Morocco were thwarted",
      "source": "Ennahar Online",
      "url": "https://www.ennaharonline.com/%d8%b6%d8%a8%d8%b7-8-%d9%83%d9%84%d8%ba-%d9%83%d9%88%d9%83%d8%a7%d9%8a%d9%8a%d9%86-%d9%88%d8%a5%d8%ad%d8%a8%d8%a7%d8%b7-%d9%85%d8%ad%d8%a7%d9%88%d9%84%d8%a7%d8%aa-%d8%a5%d8%af%d8%ae%d8%a7%d9%84-%d8%a3/",
      "published_date": "2026-04-29T11:05:03Z",
      "category": "Military"
    },
    {
      "title": "The terrorist, nicknamed “Maazo,” surrenders himself to the military authorities, with ammunition in his possession",
      "source": "Ennahar Online",
      "url": "https://www.ennaharonline.com/%d8%a7%d9%84%d8%a7%d8%b1%d9%87%d8%a7%d8%a8%d9%8a-%d8%a7%d9%84%d9%85%d9%83%d9%86%d9%89-%d9%85%d8%b9%d8%a7%d8%b2%d9%88-%d9%8a%d8%b3%d9%84%d9%85-%d9%86%d9%81%d8%b3%d9%87-%d9%84%d9%84%d8%b3%d9%84/",
      "published_date": "2026-04-29T10:49:26Z",
      "category": "Military"
    },
    {
      "title": "Strong explosion in Lebanon causes earthquake in northern Israel",
      "source": "Echorouk Online",
      "url": "https://www.echoroukonline.com/une-forte-explosion-au-liban-provoque-un-seisme-dans-le-nord-disrael",
      "published_date": "2026-04-29T10:47:42Z",
      "category": "Military"
    },
    {
      "title": "Drama in Batna: a house blown up by a gas explosion",
      "source": "TSA Algérie",
      "url": "https://www.tsa-algerie.com/drame-a-batna-une-maison-soufflee-par-une-explosion-due-au-gaz/",
      "published_date": "2026-04-29T07:50:47Z",
      "category": "Military"
    },
    {
      "title": "Seized 1.5 million hallucinogenic tablets",
      "source": "Ennahar Online",
      "url": "https://www.ennaharonline.com/%d8%ad%d8%ac%d8%b2-1-5-%d9%85%d9%84%d9%8a%d9%88%d9%86-%d9%82%d8%b1%d8%b5-%d9%85%d9%87%d9%84%d9%88%d8%b3/",
      "published_date": "2026-04-28T20:42:54Z",
      "category": "Military"
    },
    {
      "title": "Morocco, France, and the Madrid bombings",
      "source": "Echorouk Online",
      "url": "https://www.echoroukonline.com/%d8%a7%d9%84%d9%85%d8%ba%d8%b1%d8%a8-%d9%88%d9%81%d8%b1%d9%86%d8%b3%d8%a7-%d9%88%d8%aa%d9%81%d8%ac%d9%8a%d8%b1%d8%a7%d8%aa%d9%8f-%d9%85%d8%af%d8%b1%d9%8a%d8%af",
      "published_date": "2026-04-28T19:31:51Z",
      "category": "Military"
    },
    {
      "title": "Putin's advisor visits the port of Algiers",
      "source": "Ennahar Online",
      "url": "https://www.ennaharonline.com/%d9%85%d8%b3%d8%aa%d8%b4%d8%a7%d8%b1-%d8%a8%d9%88%d8%aa%d9%8a%d9%86-%d9%8a%d8%b2%d9%88%d8%b1-%d9%85%d9%8a%d9%86%d8%a7%d8%a1-%d8%a7%d9%84%d8%ac%d8%b2%d8%a7%d8%a6%d8%b1/",
      "published_date": "2026-04-28T19:17:41Z",
      "category": "Military"
    },
    {
      "title": "Military cooperation: Army General Saïd Chanegriha receives the commander of AFRICOM",
      "source": "Algerie360",
      "url": "https://www.algerie360.com/cooperation-militaire-le-general-darmee-said-chanegriha-recoit-le-commandant-de-lafricom/",
      "published_date": "2026-04-28T15:58:52Z",
      "category": "Military"
    },
    {
      "title": "Chengriha: Algeria continues to strengthen the mechanisms of the continental endeavor to eliminate terrorism and violent extremism",
      "source": "Ennahar Online",
      "url": "https://www.ennaharonline.com/%d8%b4%d9%86%d9%82%d8%b1%d9%8a%d8%ad%d8%a9-%d8%a7%d9%84%d8%ac%d8%b2%d8%a7%d8%a6%d8%b1-%d8%aa%d9%88%d8%a7%d8%b5%d9%84-%d8%aa%d8%b9%d8%b2%d9%8a%d8%b2-%d8%a2%d9%84%d9%8a%d8%a7%d8%aa-%d8%a7%d9%84%d9%85/",
      "published_date": "2026-04-28T12:13:06Z",
      "category": "Military"
    },
    {
      "title": "Lieutenant General Chengriha receives the Commander of the US Africa Command (AFRICOM)",
      "source": "Ennahar Online",
      "url": "https://www.ennaharonline.com/%d8%a7%d9%84%d9%81%d8%b1%d9%8a%d9%82-%d8%a3%d9%88%d9%84-%d8%b4%d9%86%d9%82%d8%b1%d9%8a%d8%ad%d8%a9-%d9%8a%d8%b3%d8%aa%d9%82%d8%a8%d9%84-%d9%82%d8%a7%d8%a6%d8%af-%d8%a7%d9%84%d9%82%d9%8a%d8%a7%d8%af-2/",
      "published_date": "2026-04-28T11:42:17Z",
      "category": "Military"
    },
    {
      "title": "Fight against money laundering: Algeria excludes certain profiles from trade",
      "source": "TSA Algérie",
      "url": "https://www.tsa-algerie.com/lutte-anti-blanchiment-dargent-lalgerie-exclut-certains-profils-du-commerce/",
      "published_date": "2026-04-27T15:50:10Z",
      "category": "Military"
    },
    {
      "title": "Curfew extended by 45 days in the Sahel",
      "source": "Liberté Algérie",
      "url": "https://www.liberte-algerie.com/flash-actualite/le-couvre-feu-prolonge-de-45-jours-dans-le-sahel-17",
      "published_date": "2026-04-27T14:01:00Z",
      "category": "Military"
    },
    {
      "title": "By 75%.. The Chinese “Deep Sec” offers a discount on its new model of artificial intelligence",
      "source": "Echorouk Online",
      "url": "https://www.echoroukonline.com/%d8%a8%d9%86%d8%b3%d8%a8%d8%a9-75-%d8%af%d9%8a%d8%a8-%d8%b3%d9%8a%d9%83-%d8%a7%d9%84%d8%b5%d9%8a%d9%86%d9%8a%d8%a9-%d8%aa%d9%82%d8%af%d9%85-%d8%ae%d8%b5%d9%85%d8%a7-%d8%b9%d9%84%d9%89-%d9%86",
      "published_date": "2026-04-27T11:16:19Z",
      "category": "Military"
    },
    {
      "title": "Naftal: Important regarding rubber wheels",
      "source": "Ennahar Online",
      "url": "https://www.ennaharonline.com/%d9%86%d9%81%d8%b7%d8%a7%d9%84-%d9%87%d8%a7%d9%85-%d8%a8%d8%ae%d8%b5%d9%88%d8%b5-%d8%a7%d9%84%d8%b9%d8%ac%d9%84%d8%a7%d8%aa-%d8%a7%d9%84%d9%85%d8%b7%d8%a7%d8%b7%d9%8a%d8%a9/",
      "published_date": "2026-04-30T22:10:19Z",
      "category": "Energy"
    },
    {
      "title": "OPEC: after the surprise decision of the Emirates, Algiers recalls the fundamentals",
      "source": "Algerie360",
      "url": "https://www.algerie360.com/opep-apres-la-decision-surprise-des-emirats-alger-rappelle-les-fondamentaux/",
      "published_date": "2026-04-30T10:05:57Z",
      "category": "Energy"
    },
    {
      "title": "350 Algerian institutions participate in the exhibition for Algerian products and services in Nouakchott",
      "source": "Echorouk Online",
      "url": "https://www.echoroukonline.com/350-%d9%85%d8%a4%d8%b3%d8%b3%d8%a9-%d8%ac%d8%b2%d8%a7%d8%a6%d8%b1%d9%8a%d8%a9-%d8%aa%d8%b4%d8%a7%d8%b1%d9%83-%d9%81%d9%8a-%d8%a7%d9%84%d9%85%d8%b9%d8%b1%d8%b6-%d8%a7%d9%84%d8%ae%d8%a7%d8%b5-%d8%a8",
      "published_date": "2026-04-30T09:55:14Z",
      "category": "Energy"
    },
    {
      "title": "Oil soars to 125 dollars, a boon for Algeria",
      "source": "TSA Algérie",
      "url": "https://www.tsa-algerie.com/le-petrole-flambe-a-125-dollars-une-aubaine-pour-lalgerie/",
      "published_date": "2026-04-30T07:51:51Z",
      "category": "Energy"
    },
    {
      "title": "Algeria and Poland... towards giant energy projects",
      "source": "Ennahar Online",
      "url": "https://www.ennaharonline.com/%d8%a7%d9%84%d8%ac%d8%b2%d8%a7%d8%a6%d8%b1-%d9%88%d8%a8%d9%88%d9%84%d9%86%d8%af%d8%a7-%d9%86%d8%ad%d9%88-%d9%85%d8%b4%d8%a7%d8%b1%d9%8a%d8%b9-%d8%b7%d8%a7%d9%82%d9%88%d9%8a%d8%a9-%d8%b9%d9%85%d9%84/",
      "published_date": "2026-04-29T21:24:19Z",
      "category": "Energy"
    },
    {
      "title": "OPEC: Algeria reacts to the withdrawal of the United Arab Emirates",
      "source": "TSA Algérie",
      "url": "https://www.tsa-algerie.com/opep-lalgerie-reagit-au-retrait-des-emirats-arabes-unis/",
      "published_date": "2026-04-29T18:53:10Z",
      "category": "Energy"
    },
    {
      "title": "Oil: Brent soars and approaches 120 dollars",
      "source": "TSA Algérie",
      "url": "https://www.tsa-algerie.com/petrole-le-brent-flambe-et-se-rapproche-des-120-dollars/",
      "published_date": "2026-04-29T18:40:02Z",
      "category": "Energy"
    },
    {
      "title": "An unprecedented acceleration in renewable energy projects in Algeria",
      "source": "Echorouk Online",
      "url": "https://www.echoroukonline.com/%d8%aa%d8%b3%d8%a7%d8%b1%d8%b9-%d8%ba%d9%8a%d8%b1-%d9%85%d8%b3%d8%a8%d9%88%d9%82-%d9%81%d9%8a-%d9%85%d8%b4%d8%a7%d8%b1%d9%8a%d8%b9-%d8%a7%d9%84%d8%b7%d8%a7%d9%82%d8%a7%d8%aa-%d8%a7%d9%84%d9%85%d8%aa",
      "published_date": "2026-04-29T11:10:43Z",
      "category": "Energy"
    },
    {
      "title": "Environment: A delegation from the Green Climate Fund visits Algeria",
      "source": "Ennahar Online",
      "url": "https://www.ennaharonline.com/%d8%a8%d9%8a%d8%a6%d8%a9-%d9%88%d9%81%d8%af-%d9%85%d9%86-%d8%a7%d9%84%d8%b5%d9%86%d8%af%d9%88%d9%82-%d8%a7%d9%84%d8%a3%d8%ae%d8%b6%d8%b1-%d9%84%d9%84%d9%85%d9%86%d8%a7%d8%ae-%d9%81%d9%8a-%d8%b2%d9%8a/",
      "published_date": "2026-04-29T11:04:33Z",
      "category": "Energy"
    },
    {
      "title": "PwC reveals the assets and economic potential of Algeria",
      "source": "TSA Algérie",
      "url": "https://www.tsa-algerie.com/pwc-devoile-les-atouts-et-le-potentiel-economique-de-lalgerie/",
      "published_date": "2026-04-28T20:33:37Z",
      "category": "Energy"
    },
    {
      "title": "With a capacity of 1,400 MW: Algeria has a new energy giant in this wilaya",
      "source": "Algerie360",
      "url": "https://www.algerie360.com/dune-capacite-de-1-400-mw-lalgerie-se-dote-dun-nouveau-geant-energetique-dans-cette-wilaya/",
      "published_date": "2026-04-28T11:50:32Z",
      "category": "Energy"
    },
    {
      "title": "Ajal: Localizing the industry related to renewable energies and not being limited to imports",
      "source": "Ennahar Online",
      "url": "https://www.ennaharonline.com/%d8%b9%d8%ac%d8%a7%d9%84-%d8%aa%d9%88%d8%b7%d9%8a%d9%86-%d8%a7%d9%84%d8%b5%d9%86%d8%a7%d8%b9%d8%a9-%d8%a7%d9%84%d9%85%d8%aa%d8%b9%d9%84%d9%82%d8%a9-%d8%a8%d8%a7%d9%84%d8%b7%d8%a7%d9%82%d8%a7%d8%aa/",
      "published_date": "2026-04-28T11:30:38Z",
      "category": "Energy"
    },
    {
      "title": "An Algerian-Swedish agreement to launch a program to remove carbon from the industrial sector",
      "source": "Echorouk Online",
      "url": "https://www.echoroukonline.com/%d8%a7%d8%aa%d9%81%d8%a7%d9%82%d9%8a%d8%a9-%d8%ac%d8%b2%d8%a7%d8%a6%d8%b1%d9%8a%d8%a9-%d8%b3%d9%88%d9%8a%d8%af%d9%8a%d8%a9-%d9%84%d8%a5%d8%b7%d9%84%d8%a7%d9%82-%d8%a8%d8%b1%d9%86%d8%a7%d9%85%d8%ac",
      "published_date": "2026-04-28T11:30:19Z",
      "category": "Energy"
    },
    {
      "title": "Minister of Mines: We aspire to transform into a producer for the local market and a clean global exporter",
      "source": "Ennahar Online",
      "url": "https://www.ennaharonline.com/%d9%88%d8%b2%d9%8a%d8%b1-%d8%a7%d9%84%d9%85%d9%86%d8%a7%d8%ac%d9%85-%d9%86%d8%b7%d9%85%d8%ad-%d9%84%d9%84%d8%aa%d8%ad%d9%88%d9%84-%d8%a5%d9%84%d9%89-%d9%85%d9%86%d8%aa%d8%ac-%d9%84%d9%84%d8%b3%d9%88/",
      "published_date": "2026-04-28T11:26:33Z",
      "category": "Energy"
    },
    {
      "title": "Arkab confirms Algeria's intention to strengthen its regional energy position",
      "source": "Echorouk Online",
      "url": "https://www.echoroukonline.com/%d8%b9%d8%b1%d9%82%d8%a7%d8%a8-%d9%8a%d8%a4%d9%83%d8%af-%d8%aa%d9%88%d8%ac%d9%87-%d8%a7%d9%84%d8%ac%d8%b2%d8%a7%d8%a6%d8%b1-%d9%84%d8%aa%d8%b9%d8%b2%d9%8a%d8%b2-%d9%85%d9%83%d8%a7%d9%86%d8%aa%d9%87",
      "published_date": "2026-04-28T11:09:15Z",
      "category": "Energy"
    },
    {
      "title": "Daoudi: Sonatrach's priority is the national market and securing its needs",
      "source": "Ennahar Online",
      "url": "https://www.ennaharonline.com/%d8%af%d8%a7%d9%88%d8%af%d9%8a-%d8%a3%d9%88%d9%84%d9%88%d9%8a%d8%a9-%d8%b3%d9%88%d9%86%d8%a7%d8%b7%d8%b1%d8%a7%d9%83-%d9%87%d9%8a-%d8%a7%d9%84%d8%b3%d9%88%d9%82-%d8%a7%d9%84%d9%88%d8%b7%d9%86%d9%8a/",
      "published_date": "2026-04-28T11:04:58Z",
      "category": "Energy"
    },
    {
      "title": "Arkab: Algeria's vision is to become a regional energy pole",
      "source": "Ennahar Online",
      "url": "https://www.ennaharonline.com/%d8%b9%d8%b1%d9%82%d8%a7%d8%a8-%d8%b1%d8%a4%d9%8a%d8%a9-%d8%a7%d9%84%d8%ac%d8%b2%d8%a7%d8%a6%d8%b1-%d8%aa%d9%82%d9%88%d9%85-%d8%b9%d9%84%d9%89-%d8%a7%d9%84%d8%aa%d8%ad%d9%88%d9%84-%d8%a5%d9%84%d9%89/",
      "published_date": "2026-04-28T10:42:47Z",
      "category": "Energy"
    },
    {
      "title": "Algeria launches construction of a $1.4 billion power plant",
      "source": "TSA Algérie",
      "url": "https://www.tsa-algerie.com/lalgerie-lance-le-chantier-dune-centrale-electrique-pour-14-milliard/",
      "published_date": "2026-04-27T19:52:48Z",
      "category": "Energy"
    },
    {
      "title": "Arkab will participate tomorrow in the activities of the second edition of the CEO Survey",
      "source": "Ennahar Online",
      "url": "https://www.ennaharonline.com/%d8%b9%d8%b1%d9%82%d8%a7%d8%a8-%d9%8a%d8%b4%d8%a7%d8%b1%d9%83-%d8%ba%d8%af%d8%a7-%d9%81%d9%8a-%d9%81%d8%b9%d8%a7%d9%84%d9%8a%d8%a7%d8%aa-%d8%a7%d9%84%d9%86%d8%b3%d8%ae%d8%a9-%d8%a7%d9%84%d8%ab%d8%a7/",
      "published_date": "2026-04-27T11:26:04Z",
      "category": "Energy"
    },
    {
      "title": "Jet fuel crisis: Transavia cancels flights in May and June 2026 and increases prices",
      "source": "Algerie360",
      "url": "https://www.algerie360.com/crise-du-kerosene-transavia-annule-des-vols-en-mai-et-juin-2026-et-augmente-ses-prix/",
      "published_date": "2026-04-27T11:07:58Z",
      "category": "Energy"
    },
    {
      "title": "Eid 2026 in Algeria: 6 steps to buy imported sheep",
      "source": "TSA Algérie",
      "url": "https://www.tsa-algerie.com/aid-2026-en-algerie-6-etapes-pour-acheter-un-mouton-importe/",
      "published_date": "2026-04-30T20:40:51Z",
      "category": "Economy"
    },
    {
      "title": "Subsidies in Algeria: Tebboune stays the course",
      "source": "TSA Algérie",
      "url": "https://www.tsa-algerie.com/subventions-en-algerie-tebboune-maintient-le-cap/",
      "published_date": "2026-04-30T20:20:44Z",
      "category": "Economy"
    },
    {
      "title": "These are the most important files studied by the government meeting today",
      "source": "Echorouk Online",
      "url": "https://www.echoroukonline.com/%d9%87%d8%b0%d9%87-%d8%a3%d9%87%d9%85-%d8%a7%d9%84%d9%85%d9%84%d9%81%d8%a7%d8%aa-%d8%a7%d9%84%d8%aa%d9%8a-%d8%af%d8%b1%d8%b3%d9%87%d8%a7-%d8%a7%d8%ac%d8%aa%d9%85%d8%a7%d8%b9-%d8%a7%d9%84%d8%ad%d9%83",
      "published_date": "2026-04-30T16:13:45Z",
      "category": "Economy"
    },
    {
      "title": "Towards opening new horizons for Algerian products in the Russian market",
      "source": "Echorouk Online",
      "url": "https://www.echoroukonline.com/%d9%86%d8%ad%d9%88-%d9%81%d8%aa%d8%ad-%d8%a2%d9%81%d8%a7%d9%82-%d8%ac%d8%af%d9%8a%d8%af%d8%a9-%d8%a3%d9%85%d8%a7%d9%85-%d8%a7%d9%84%d9%85%d9%86%d8%aa%d8%ac%d8%a7%d8%aa-%d8%a7%d9%84%d8%ac%d8%b2%d8%a7",
      "published_date": "2026-04-30T15:34:31Z",
      "category": "Economy"
    },
    {
      "title": "China – Africa: Xi Jinping announces “zero tariffs” for 53 African countries from this date",
      "source": "Algerie360",
      "url": "https://www.algerie360.com/chine-afrique-xi-jinping-annonce-le-zero-tarif-pour-53-pays-africains-des-cette-date/",
      "published_date": "2026-04-30T15:23:02Z",
      "category": "Economy"
    },
    {
      "title": "Sale of imported sheep in KG: Zebdi’s solution so that every Algerian pays the “fair price”",
      "source": "Algerie360",
      "url": "https://www.algerie360.com/vente-des-moutons-importes-au-kg-la-solution-de-zebdi-pour-que-chaque-algerien-paie-le-juste-prix/",
      "published_date": "2026-04-30T12:42:01Z",
      "category": "Economy"
    },
    {
      "title": "Coming from Spain.. The port of Tennis receives a fourth shipment loaded with 16,250 heads of sheep",
      "source": "Echorouk Online",
      "url": "https://www.echoroukonline.com/%d9%82%d8%a7%d8%af%d9%85%d8%a9-%d9%85%d9%86-%d8%a5%d8%b3%d8%a8%d8%a7%d9%86%d9%8a%d8%a7-%d9%85%d9%8a%d9%86%d8%a7%d8%a1-%d8%aa%d9%86%d8%b3-%d9%8a%d8%b3%d8%aa%d9%82%d8%a8%d9%84-%d8%b4%d8%ad%d9%86%d8%a9-2",
      "published_date": "2026-04-30T10:36:51Z",
      "category": "Economy"
    },
    {
      "title": "The Ministry of Health offers scholarships to study in China",
      "source": "Ennahar Online",
      "url": "https://www.ennaharonline.com/%d9%88%d8%b2%d8%a7%d8%b1%d8%a9-%d8%a7%d9%84%d8%b5%d8%ad%d8%a9-%d8%aa%d9%82%d8%af%d9%85-%d9%85%d9%86%d8%ad%d8%a7-%d9%84%d9%84%d8%af%d8%b1%d8%a7%d8%b3%d8%a9-%d8%a8%d8%a7%d9%84%d8%b5%d9%8a%d9%86/",
      "published_date": "2026-04-30T10:33:17Z",
      "category": "Economy"
    },
    {
      "title": "An important announcement for the benefit of economic customers",
      "source": "Echorouk Online",
      "url": "https://www.echoroukonline.com/%d8%a5%d8%b9%d9%84%d8%a7%d9%86-%d9%87%d8%a7%d9%85-%d9%84%d9%81%d8%a7%d8%a6%d8%af%d8%a9-%d8%a7%d9%84%d9%85%d8%aa%d8%b9%d8%a7%d9%85%d9%84%d9%8a%d9%86-%d8%a7%d9%84%d8%a7%d9%82%d8%aa%d8%b5%d8%a7%d8%af",
      "published_date": "2026-04-30T09:31:03Z",
      "category": "Economy"
    },
    {
      "title": "From the port of Skikda... exporting approximately 10 thousand tons of cement to Libya",
      "source": "Echorouk Online",
      "url": "https://www.echoroukonline.com/%d9%85%d9%86-%d9%85%d9%8a%d9%86%d8%a7%d8%a1-%d8%b3%d9%83%d9%8a%d9%83%d8%af%d8%a9-%d8%aa%d8%b5%d8%af%d9%8a%d8%b1-%d9%82%d8%b1%d8%a7%d8%a8%d8%a9-10-%d8%a2%d9%84%d8%a7%d9%81-%d8%b7%d9%86-%d9%85%d9%86",
      "published_date": "2026-04-29T19:49:07Z",
      "category": "Economy"
    },
    {
      "title": "Taxes are in effect across 11 states to erase debts before 2011!",
      "source": "Echorouk Online",
      "url": "https://www.echoroukonline.com/%d8%a7%d9%84%d8%b6%d8%b1%d8%a7%d8%a6%d8%a8-%d9%81%d9%8a-%d8%ae%d8%b1%d8%ac%d8%a7%d8%aa-%d8%b9%d8%a8%d8%b1-11-%d9%88%d9%84%d8%a7%d9%8a%d8%a9-%d9%84%d8%ad%d8%b0%d9%81-%d8%af%d9%8a%d9%88%d9%86-%d9%82",
      "published_date": "2026-04-29T19:15:10Z",
      "category": "Economy"
    },
    {
      "title": "An exciting final with many backgrounds between Al-Ittihad and Belouizdad",
      "source": "Echorouk Online",
      "url": "https://www.echoroukonline.com/%d9%86%d9%87%d8%a7%d8%a6%d9%8a-%d9%85%d8%ab%d9%8a%d8%b1-%d8%a8%d8%ae%d9%84%d9%81%d9%8a%d8%a7%d8%aa-%d9%83%d8%ab%d9%8a%d8%b1%d8%a9-%d8%a8%d9%8a%d9%86-%d8%a7%d9%84%d8%a7%d8%aa%d8%ad%d8%a7%d8%af-%d9%88",
      "published_date": "2026-04-29T19:11:02Z",
      "category": "Economy"
    },
    {
      "title": "Algeria Post... Important for the owners of these accounts",
      "source": "Ennahar Online",
      "url": "https://www.ennaharonline.com/%d8%a8%d8%b1%d9%8a%d8%af-%d8%a7%d9%84%d8%ac%d8%b2%d8%a7%d8%a6%d8%b1-%d9%87%d8%a7%d9%85-%d9%84%d8%a3%d8%b5%d8%ad%d8%a7%d8%a8-%d9%87%d8%b0%d9%87-%d8%a7%d9%84%d8%ad%d8%b3%d8%a7%d8%a8%d8%a7%d8%aa/",
      "published_date": "2026-04-29T18:24:44Z",
      "category": "Economy"
    },
    {
      "title": "Djezzy reveals increased financial results in the 1st quarter of 2026",
      "source": "TSA Algérie",
      "url": "https://www.tsa-algerie.com/djezzy-devoile-des-resultats-financiers-en-hausse-au-1%e1%b5%89%ca%b3-trimestre-2026/",
      "published_date": "2026-04-29T17:00:30Z",
      "category": "Economy"
    },
    {
      "title": "The three main fears of Algerian bosses",
      "source": "TSA Algérie",
      "url": "https://www.tsa-algerie.com/les-trois-principales-craintes-des-patrons-algeriens/",
      "published_date": "2026-04-28T20:26:29Z",
      "category": "Economy"
    },
    {
      "title": "New conditions for banks’ external obligations starting in May 2026",
      "source": "Echorouk Online",
      "url": "https://www.echoroukonline.com/%d8%b4%d8%b1%d9%88%d8%b7-%d8%ac%d8%af%d9%8a%d8%af%d8%a9-%d9%84%d9%84%d8%a7%d9%84%d8%aa%d8%b2%d8%a7%d9%85%d8%a7%d8%aa-%d8%a7%d9%84%d8%ae%d8%a7%d8%b1%d8%ac%d9%8a%d8%a9-%d9%84%d9%84%d8%a8%d9%86%d9%88",
      "published_date": "2026-04-28T19:30:53Z",
      "category": "Economy"
    },
    {
      "title": "Officially ending the “Covid-19” tax exemption system!",
      "source": "Echorouk Online",
      "url": "https://www.echoroukonline.com/%d8%a5%d9%86%d9%87%d8%a7%d8%a1-%d8%a7%d9%84%d8%b9%d9%85%d9%84-%d8%b1%d8%b3%d9%85%d9%8a%d8%a7-%d8%a8%d9%86%d8%b8%d8%a7%d9%85-%d8%a7%d9%84%d8%a5%d8%b9%d9%81%d8%a7%d8%a1%d8%a7%d8%aa-%d8%a7%d9%84%d8%ac",
      "published_date": "2026-04-28T19:10:53Z",
      "category": "Economy"
    },
    {
      "title": "Algeria rises to 7th rank among Arab importers of this high-tech product",
      "source": "Algerie360",
      "url": "https://www.algerie360.com/lalgerie-se-hisse-au-7eme-rang-des-importateurs-arabes-de-ce-produit-high-tech/",
      "published_date": "2026-04-28T14:40:22Z",
      "category": "Economy"
    },
    {
      "title": "Oran: a real estate project condemns the entrance to a mosque",
      "source": "TSA Algérie",
      "url": "https://www.tsa-algerie.com/oran-un-chantier-immobilier-condamne-lentree-dune-mosquee/",
      "published_date": "2026-04-28T14:27:01Z",
      "category": "Economy"
    },
    {
      "title": "Bukhari: Algeria has resolutely engaged in integrating sustainable development goals into its national policies",
      "source": "Ennahar Online",
      "url": "https://www.ennaharonline.com/%d8%a8%d9%88%d8%ae%d8%a7%d8%b1%d9%8a-%d8%a7%d9%84%d8%ac%d8%b2%d8%a7%d8%a6%d8%b1-%d8%a7%d9%86%d8%ae%d8%b1%d8%b7%d8%aa-%d8%a8%d8%b9%d8%b2%d9%85-%d9%81%d9%8a-%d8%a5%d8%af%d9%85%d8%a7%d8%ac-%d8%a3%d9%87/",
      "published_date": "2026-04-28T11:55:23Z",
      "category": "Economy"
    },
    {
      "title": "GLP-1 Drugs: What the Science Really Reveals About Ozempic",
      "source": "Algerie360",
      "url": "https://www.algerie360.com/medicaments-glp-1-ce-que-la-science-revele-vraiment-sur-lozempic/",
      "published_date": "2026-04-30T22:53:25Z",
      "category": "Local Events"
    },
    {
      "title": "Greens: After Zidane, Mandrea operated successfully",
      "source": "DzFoot",
      "url": "https://www.dzfoot.com/verts-deurope/verts-apres-zidane-mandrea-opere-avec-succes-292236.html?utm_source=rss_feed&utm_medium=link&utm_campaign=unknown",
      "published_date": "2026-04-30T21:45:46Z",
      "category": "Local Events"
    },
    {
      "title": "Lamine Ndiaye: “I said it before, the final is won and not played...and our players deserve this coronation.”",
      "source": "Ennahar Online",
      "url": "https://www.ennaharonline.com/%d9%84%d8%a7%d9%85%d9%8a%d9%86-%d9%86%d8%af%d8%a7%d9%8a%d9%82%d9%84%d8%aa%d9%87%d8%a7-%d8%b3%d8%a7%d8%a8%d9%82%d8%a7%d9%8b-%d8%a7%d9%84%d9%86%d9%87%d8%a7%d8%a6%d9%8a-%d9%8a%d9%8f%d8%b1%d8%a8%d8%ad/",
      "published_date": "2026-04-30T21:34:21Z",
      "category": "Local Events"
    },
    {
      "title": "Bin Bout: “Ready to represent the national team in the World Cup”",
      "source": "Ennahar Online",
      "url": "https://www.ennaharonline.com/%d8%a8%d9%86-%d8%a8%d9%88%d8%b7-%d8%ac%d8%a7%d9%87%d8%b2-%d9%84%d8%aa%d9%85%d8%ab%d9%8a%d9%84-%d8%a7%d9%84%d9%85%d9%86%d8%aa%d8%ae%d8%a8-%d8%a7%d9%84%d9%88%d8%b7%d9%86%d9%8a-%d9%81%d9%8a-%d8%a7/",
      "published_date": "2026-04-30T21:03:33Z",
      "category": "Local Events"
    },
    {
      "title": "Souk Ahras: A person was arrested and 4 quintals of bananas destined for speculation were seized",
      "source": "Ennahar Online",
      "url": "https://www.ennaharonline.com/%d8%b3%d9%88%d9%82-%d8%a3%d9%87%d8%b1%d8%a7%d8%b3-%d8%aa%d9%88%d9%82%d9%8a%d9%81-%d8%b4%d8%ae%d8%b5-%d9%88%d8%ad%d8%ac%d8%b2-4-%d9%82%d9%86%d8%a7%d8%b7%d9%8a%d8%b1-%d9%85%d9%86-%d8%a7%d9%84%d9%85/",
      "published_date": "2026-04-30T20:06:53Z",
      "category": "Local Events"
    },
    {
      "title": "Djelfa.. 7 injured in a collision between two cars in the “Wouroud” area",
      "source": "Ennahar Online",
      "url": "https://www.ennaharonline.com/%d8%a7%d9%84%d8%ac%d9%84%d9%81%d8%a9-7-%d8%ac%d8%b1%d8%ad%d9%89-%d9%81%d9%8a-%d8%ad%d8%a7%d8%af%d8%ab-%d8%a7%d8%b5%d8%b7%d8%af%d8%a7%d9%85-%d8%a8%d9%8a%d9%86-%d8%b3%d9%8a%d8%a7%d8%b1%d8%aa%d9%8a-3/",
      "published_date": "2026-04-30T19:11:38Z",
      "category": "Local Events"
    },
    {
      "title": "Two children died by drowning in a pool of water in El Obeid, Sidi Sheikh",
      "source": "Ennahar Online",
      "url": "https://www.ennaharonline.com/%d9%88%d9%81%d8%a7%d8%a9-%d8%b7%d9%81%d9%84%d9%8a%d9%86-%d8%ba%d8%b1%d9%82%d9%8b%d8%a7-%d9%81%d9%8a-%d8%a8%d8%b1%d9%83%d8%a9-%d9%85%d8%a7%d8%a6%d9%8a%d8%a9-%d8%a8%d8%a7%d9%84%d8%a3%d8%a8%d9%8a%d8%b6/",
      "published_date": "2026-04-30T18:46:31Z",
      "category": "Local Events"
    },
    {
      "title": "Cup: La Decima for the USMA! (video)",
      "source": "DzFoot",
      "url": "https://www.dzfoot.com/football-en-algerie/coupe-la-decima-pour-lusma-video-292222.html?utm_source=rss_feed&utm_medium=link&utm_campaign=unknown",
      "published_date": "2026-04-30T18:34:40Z",
      "category": "Local Events"
    },
    {
      "title": "Alfaf congratulates USM Algeria after winning the Algeria Cup",
      "source": "Ennahar Online",
      "url": "https://www.ennaharonline.com/%d8%a7%d9%84%d9%81%d8%a7%d9%81-%d8%aa%d9%87%d9%86%d9%91%d8%a6-%d8%a7%d8%aa%d8%ad%d8%a7%d8%af-%d8%a7%d9%84%d8%b9%d8%a7%d8%b5%d9%85%d8%a9-%d8%a8%d8%b9%d8%af-%d8%a7%d9%84%d8%aa%d8%aa%d9%88%d9%8a%d8%ac/",
      "published_date": "2026-04-30T18:34:05Z",
      "category": "Local Events"
    },
    {
      "title": "Algerian Cup Final: USMA beats CRB and wins the Décima",
      "source": "Algerie360",
      "url": "https://www.algerie360.com/finale-coupe-dalgerie-lusma-bat-le-crb-et-soffre-la-decima/",
      "published_date": "2026-04-30T18:24:01Z",
      "category": "Local Events"
    },
    {
      "title": "How to purchase Eid sacrifice via the “Adahi” platform?",
      "source": "Echorouk Online",
      "url": "https://www.echoroukonline.com/%d9%83%d9%8a%d9%81-%d9%8a%d8%aa%d9%85-%d8%a7%d9%82%d8%aa%d9%86%d8%a7%d8%a1-%d8%a3%d8%b6%d8%ad%d9%8a%d8%a9-%d8%a7%d9%84%d8%b9%d9%8a%d8%af-%d8%b9%d8%a8%d8%b1-%d9%85%d9%86%d8%b5%d8%a9-%d8%a3%d8%b6",
      "published_date": "2026-04-30T17:55:58Z",
      "category": "Local Events"
    },
    {
      "title": "Algeria – Tunisia: smuggling reaches strawberries",
      "source": "TSA Algérie",
      "url": "https://www.tsa-algerie.com/algerie-tunisie-la-contrebande-atteint-la-fraise/",
      "published_date": "2026-04-30T17:05:37Z",
      "category": "Local Events"
    },
    {
      "title": "EN: Here is the ticket office for the Netherlands!",
      "source": "DzFoot",
      "url": "https://www.dzfoot.com/equipes-nationales/en-voici-la-billetterie-pour-les-pays-bas-292208.html?utm_source=rss_feed&utm_medium=link&utm_campaign=unknown",
      "published_date": "2026-04-30T16:04:52Z",
      "category": "Local Events"
    },
    {
      "title": "MSF suspends its operations",
      "source": "Liberté Algérie",
      "url": "https://www.liberte-algerie.com/flash-actualite/msf-suspend-ses-operations-14",
      "published_date": "2026-04-30T15:58:00Z",
      "category": "Local Events"
    },
    {
      "title": "Pension increased? Here's how to check the value without waiting",
      "source": "Algerie360",
      "url": "https://www.algerie360.com/pension-revue-a-la-hausse-voici-comment-verifier-la-valeur-sans-attendre/",
      "published_date": "2026-04-30T15:37:28Z",
      "category": "Local Events"
    },
    {
      "title": "Steel industry: AQS and Tosyali launch the race towards excellence in Algeria",
      "source": "Algerie360",
      "url": "https://www.algerie360.com/siderurgie-aqs-et-tosyali-lance-la-course-vers-lexcellence-en-algerie/",
      "published_date": "2026-04-30T15:24:49Z",
      "category": "Local Events"
    },
    {
      "title": "How the 22 met at Lyes Derriche (July 25, 1954)",
      "source": "Liberté Algérie",
      "url": "https://www.liberte-algerie.com/videos/comment-les-22-se-sont-reunis-chez-lyes-derriche-25-juillet-1954-5",
      "published_date": "2026-04-30T15:06:00Z",
      "category": "Local Events"
    },
    {
      "title": "France: the far right claims a first victory against Imane Khelif",
      "source": "TSA Algérie",
      "url": "https://www.tsa-algerie.com/france-lextreme-droite-revendique-une-premiere-victoire-contre-imane-khelif/",
      "published_date": "2026-04-30T15:00:30Z",
      "category": "Local Events"
    },
    {
      "title": "Millions of people lack food during Ramadan",
      "source": "Liberté Algérie",
      "url": "https://www.liberte-algerie.com/flash-actualite/des-millions-de-personnes-manquent-de-nourriture-durant-le-ramadan-13",
      "published_date": "2026-04-30T14:27:00Z",
      "category": "Local Events"
    },
    {
      "title": "Postponement until April 20 of the trial of the accused in the Metidji group affair",
      "source": "Liberté Algérie",
      "url": "https://www.liberte-algerie.com/flash-actualite/report-au-20-avril-du-proces-des-accuses-dans-l-affaire-du-groupe-metidji-16",
      "published_date": "2026-04-30T13:35:00Z",
      "category": "Local Events"
    }
  ]
}